Workbook

Sheet Processed Data
A1: Contact Id | B1: Customer Id | C1: Lead Reference | D1: List Id | E1: List Name | F1: Title | G1: Firstname | H1: Lastname | I1: Gender | J1: Last Outcome | K1: Outcome Description | L1: Called Count | M1: Last Called Date | N1: Last User | O1: Created At | P1: Updated At | Q1: Address1 | R1: Address2 | S1: Address3 | T1: Town | U1: County | V1: Country | W1: Postcode | X1: Email Address | Y1: Tel1 | Z1: Tel2 | AA1: Tel3 | AB1: Tel4 | AC1: Tel5 | AD1: Tel6 | AE1: Owner Username | AF1: Security Phrase | AG1: Source Reference | AH1: Industry | AI1: Company Name | AJ1: Website | AK1: Customer Reference | AL1: Dob
A2: 12861843 | B2: 230fc6b9-dcd2-4d67-8acc-8621b3942bcd | D2: 11129 | E2: Vodacom Funeral Upsell Jan 26 | G2: MUHAMED KAMIL | H2: HANIFF | J2: AE | K2: Auto Engaged | L2: 38 | M2: 2026-06-29 13:49:12 | N2: system | O2: 2026-01-13 10:54:41 | P2: 2026-01-13 10:54:41 | X2: mkhaniff26@gmail.com | Y2: 27737860917
A3: 12880567 | B3: 1d331d12-8b40-4748-992b-5c6b4d0ee4a9 | D3: 11129 | E3: Vodacom Funeral Upsell Jan 26 | G3: AARON | H3: SIBIYA | J3: AA | K3: Answering Machine Autodial | L3: 38 | M3: 2026-06-29 13:49:10 | N3: system | O3: 2026-01-14 13:10:31 | P3: 2026-01-14 13:10:31 | Y3: 27711440064
A4: 12880573 | B4: 5a5217f3-ba6e-4c62-81a3-d5aa19bdf69a | D4: 11129 | E4: Vodacom Funeral Upsell Jan 26 | G4: Ntswaki | H4: Nyaphuli | J4: AE | K4: Auto Engaged | L4: 38 | M4: 2026-06-29 13:49:10 | N4: system | O4: 2026-01-14 13:10:31 | P4: 2026-01-14 13:10:31 | X4: nyaphulintswaki0@gmail.com | Y4: 27728390401
A5: 12880649 | B5: cd696212-a4f4-4fe8-8e86-af4763b4da02 | D5: 11129 | E5: Vodacom Funeral Upsell Jan 26 | G5: RACHEL | H5: LEWELE | J5: AA | K5: Answering Machine Autodial | L5: 38 | M5: 2026-06-29 13:49:10 | N5: system | O5: 2026-01-14 13:10:31 | P5: 2026-01-14 13:10:31 | Y5: 27824219325
A6: 12880667 | B6: 4e3afbe3-a2e1-4cc7-8ea8-c7268d4a7904 | D6: 11129 | E6: Vodacom Funeral Upsell Jan 26 | G6: XOLELWA | H6: NTANTISO | J6: ADC | K6: Auto Dial Disconnected | L6: 38 | M6: 2026-06-29 13:49:10 | N6: system | O6: 2026-01-14 13:10:31 | P6: 2026-01-14 13:10:31 | Y6: 27822034998
A7: 12879915 | B7: 200bc3fb-7473-4a22-904c-3b95b26b74f1 | D7: 11129 | E7: Vodacom Funeral Upsell Jan 26 | G7: MASILO VICUS | H7: MODISHA | J7: AE | K7: Auto Engaged | L7: 38 | M7: 2026-06-29 13:49:09 | N7: system | O7: 2026-01-14 13:10:31 | P7: 2026-01-14 13:10:31 | X7: modisham@gmail.com | Y7: 27661755435
A8: 12879943 | B8: 51a0ff7d-71a3-4d18-a4c6-c0cb69cc1d64 | D8: 11129 | E8: Vodacom Funeral Upsell Jan 26 | G8: SIYANDA IAN | H8: MQADI | J8: AE | K8: Auto Engaged | L8: 38 | M8: 2026-06-29 13:49:09 | N8: system | O8: 2026-01-14 13:10:31 | P8: 2026-01-14 13:10:31 | X8: siyandamqadi@outlook.com | Y8: 27798938261
A9: 12880504 | B9: a527063d-f580-49c2-9ca2-95d0e70f45fc | D9: 11129 | E9: Vodacom Funeral Upsell Jan 26 | G9: Francois | H9: van Rensburg | J9: AE | K9: Auto Engaged | L9: 38 | M9: 2026-06-29 13:49:09 | N9: system | O9: 2026-01-14 13:10:31 | P9: 2026-01-14 13:10:31 | X9: francoisvr.wbc@gmail.com | Y9: 27674639387
A10: 12880669 | B10: a58e366f-e392-4e58-8f68-d2e7bb7e90d2 | D10: 11129 | E10: Vodacom Funeral Upsell Jan 26 | G10: TSHOARO ISAAC | H10: MODISADIFE | J10: AE | K10: Auto Engaged | L10: 38 | M10: 2026-06-29 13:49:07 | N10: system | O10: 2026-01-14 13:10:31 | P10: 2026-01-14 13:10:31 | X10: tshoaromodisadife@gmail.com | Y10: 27824356473
A11: 12880308 | B11: a42b843d-16b0-4a5a-811b-5e7820879ff5 | D11: 11129 | E11: Vodacom Funeral Upsell Jan 26 | G11: Louvine | H11: Jacobs | J11: AE | K11: Auto Engaged | L11: 38 | M11: 2026-06-29 13:48:59 | N11: system | O11: 2026-01-14 13:10:31 | P11: 2026-01-14 13:10:31 | X11: vinawp1@gmail.com | Y11: 27714532304
A12: 12880334 | B12: 44477fb6-e76b-4d4d-a2be-d2c31235d397 | D12: 11129 | E12: Vodacom Funeral Upsell Jan 26 | G12: Reagan | H12: August | J12: AA | K12: Answering Machine Autodial | L12: 38 | M12: 2026-06-29 13:48:59 | N12: system | O12: 2026-01-14 13:10:31 | P12: 2026-01-22 09:27:17 | X12: Augustreagan@45gmail.com | Y12: 27828119860
A13: 12880415 | B13: 8c6f3bc2-7562-4c0f-af93-f74c8ed055bb | D13: 11129 | E13: Vodacom Funeral Upsell Jan 26 | G13: ZANELE | H13: MAC | J13: TDN | K13: Temporary Disconnected Number | L13: 38 | M13: 2026-06-29 13:48:59 | N13: system | O13: 2026-01-14 13:10:31 | P13: 2026-01-14 13:10:31 | Y13: 27674942113
A14: 12880440 | B14: 26d98230-85af-43dd-a429-78f13ca09e92 | D14: 11129 | E14: Vodacom Funeral Upsell Jan 26 | G14: PHILANI | H14: SIBHARU | J14: AA | K14: Answering Machine Autodial | L14: 38 | M14: 2026-06-29 13:48:59 | N14: system | O14: 2026-01-14 13:10:31 | P14: 2026-01-14 13:10:31 | Y14: 27822361632
A15: 12880460 | B15: 99b91130-a2a5-4b84-99b4-65db7cb846a2 | D15: 11129 | E15: Vodacom Funeral Upsell Jan 26 | G15: Brilliant | H15: Ratau | J15: ADC | K15: Auto Dial Disconnected | L15: 38 | M15: 2026-06-29 13:48:59 | N15: system | O15: 2026-01-14 13:10:31 | P15: 2026-01-14 13:10:31 | X15: onkgomoditseratau@gmail.com | Y15: 27774531054
A16: 12880279 | B16: 767a0d2e-5dfe-47a7-81f1-efb2320836c1 | D16: 11129 | E16: Vodacom Funeral Upsell Jan 26 | G16: DINEO | H16: RUITER | J16: AE | K16: Auto Engaged | L16: 38 | M16: 2026-06-29 13:48:58 | N16: system | O16: 2026-01-14 13:10:31 | P16: 2026-01-14 13:10:31 | Y16: 27727720345
A17: 12880254 | B17: b545f2d6-7180-48c0-adeb-0406bac7b361 | D17: 11129 | E17: Vodacom Funeral Upsell Jan 26 | G17: ALECIA | H17: CHETTY | J17: AE | K17: Auto Engaged | L17: 38 | M17: 2026-06-29 13:48:57 | N17: system | O17: 2026-01-14 13:10:31 | P17: 2026-01-14 13:10:31 | X17: aleciarchetty@gmail.com | Y17: 27637860518
A18: 12880226 | B18: 3080eb0c-365a-4c55-97c8-dc3b07ff126b | D18: 11129 | E18: Vodacom Funeral Upsell Jan 26 | G18: ZIKHONA | H18: QUTHU | J18: AE | K18: Auto Engaged | L18: 38 | M18: 2026-06-29 13:48:54 | N18: system | O18: 2026-01-14 13:10:31 | P18: 2026-01-14 13:10:31 | X18: zickquthu@gmail.com | Y18: 27684288353
A19: 12880152 | B19: 28189220-04a7-4fc4-a062-506f05e774ab | D19: 11129 | E19: Vodacom Funeral Upsell Jan 26 | G19: MABUTI | H19: NYAMBOSE | J19: AE | K19: Auto Engaged | L19: 38 | M19: 2026-06-29 13:48:54 | N19: system | O19: 2026-01-14 13:10:31 | P19: 2026-01-14 13:10:31 | Y19: 27661524055
A20: 12880166 | B20: 3aa71ee4-0792-47a3-b1c4-1477f9f4e77a | D20: 11129 | E20: Vodacom Funeral Upsell Jan 26 | G20: KLEINBOOI | H20: SIESAAR | J20: AE | K20: Auto Engaged | L20: 38 | M20: 2026-06-29 13:48:54 | N20: system | O20: 2026-01-14 13:10:31 | P20: 2026-01-14 13:10:31 | Y20: 27799080989
A21: 12880177 | B21: 3fdfdd54-730f-4987-8061-82d82876457e | D21: 11129 | E21: Vodacom Funeral Upsell Jan 26 | G21: KGOTSO | H21: MOREKI | J21: TDN | K21: Temporary Disconnected Number | L21: 38 | M21: 2026-06-29 13:48:54 | N21: system | O21: 2026-01-14 13:10:31 | P21: 2026-01-14 13:10:31 | Y21: 27726889566
A22: 12880150 | B22: f64d2903-7a89-4f63-b295-b3e477ef90ea | D22: 11129 | E22: Vodacom Funeral Upsell Jan 26 | G22: GERT DIEDERICK JOHANNES | H22: KRUGER | J22: AE | K22: Auto Engaged | L22: 38 | M22: 2026-06-29 13:48:51 | N22: system | O22: 2026-01-14 13:10:31 | P22: 2026-01-14 13:10:31 | X22: gert02230@gmail.com | Y22: 27762963500
A23: 12900000 | B23: 281e358f-320b-4ca5-9f9d-d4e01bd01ef2 | D23: 11129 | E23: Vodacom Funeral Upsell Jan 26 | G23: MUZI | H23: MOTAUNG | J23: ADC | K23: Auto Dial Disconnected | L23: 38 | M23: 2026-06-29 13:48:49 | N23: system | O23: 2026-01-14 13:10:31 | P23: 2026-01-14 13:10:31 | Y23: 27791483971
A24: 12880111 | B24: 32a49577-4d81-40ce-8155-64e1ed70eec1 | D24: 11129 | E24: Vodacom Funeral Upsell Jan 26 | G24: VUYOLWETHU | H24: KHAMTSHA | J24: TDN | K24: Temporary Disconnected Number | L24: 38 | M24: 2026-06-29 13:48:49 | N24: system | O24: 2026-01-14 13:10:31 | P24: 2026-01-14 13:10:31 | Y24: 27609242690
A25: 12880135 | B25: c63327a5-8a19-4aab-a273-43f4878b1318 | D25: 11129 | E25: Vodacom Funeral Upsell Jan 26 | G25: THAPELO | H25: MOKOBE | J25: TDN | K25: Temporary Disconnected Number | L25: 38 | M25: 2026-06-29 13:48:49 | N25: system | O25: 2026-01-14 13:10:31 | P25: 2026-01-14 13:10:31 | Y25: 27720286358
A26: 12880139 | B26: 3c6e734d-8e3b-4608-81a3-b750493348e7 | D26: 11129 | E26: Vodacom Funeral Upsell Jan 26 | G26: AOBAKWE | H26: DIKOBE | J26: A | K26: Answering Machine | L26: 38 | M26: 2026-06-29 13:48:49 | N26: Karabo Mpinga | O26: 2026-01-14 13:10:31 | P26: 2026-01-14 13:10:31 | Y26: 27673419179
A27: 12879852 | B27: 108342d9-37d0-466b-9e2c-9eb098575b8a | D27: 11129 | E27: Vodacom Funeral Upsell Jan 26 | G27: kate | H27: kate | J27: TDN | K27: Temporary Disconnected Number | L27: 38 | M27: 2026-06-29 13:48:48 | N27: system | O27: 2026-01-14 13:10:31 | P27: 2026-01-14 13:10:31 | X27: katemafatshe@gmail.com | Y27: 27649634821
A28: 12879987 | B28: ba23628d-c231-40ac-9b29-c0dbe99ca77b | D28: 11129 | E28: Vodacom Funeral Upsell Jan 26 | G28: LIKHONA | H28: MDAYIDAYI | J28: TDN | K28: Temporary Disconnected Number | L28: 38 | M28: 2026-06-29 13:48:47 | N28: system | O28: 2026-01-14 13:10:31 | P28: 2026-01-14 13:10:31 | Y28: 27796559406
A29: 12880089 | B29: 644699d7-c1b4-4b6d-af44-5fcee0b59300 | D29: 11129 | E29: Vodacom Funeral Upsell Jan 26 | G29: keitumetse | H29: mashele | J29: AA | K29: Answering Machine Autodial | L29: 38 | M29: 2026-06-29 13:48:45 | N29: system | O29: 2026-01-14 13:10:31 | P29: 2026-01-14 13:10:31 | X29: keitumetsemashele604@gmail.com | Y29: 27713065725
A30: 12880054 | B30: eecfd5ef-ed23-4499-9416-545a9bf55569 | D30: 11129 | E30: Vodacom Funeral Upsell Jan 26 | G30: Faheem | H30: Hajat | J30: ADC | K30: Auto Dial Disconnected | L30: 38 | M30: 2026-06-29 13:48:43 | N30: system | O30: 2026-01-14 13:10:31 | P30: 2026-01-14 13:10:31 | X30: faheemhajat@gmail.com | Y30: 27797945766
A31: 12880087 | B31: 0c716e9d-5cf0-45eb-837e-d85cb3305e21 | D31: 11129 | E31: Vodacom Funeral Upsell Jan 26 | G31: KHANYISA | H31: SIGABA | J31: AA | K31: Answering Machine Autodial | L31: 38 | M31: 2026-06-29 13:48:43 | N31: system | O31: 2026-01-14 13:10:31 | P31: 2026-01-14 13:10:31 | Y31: 27818448701
A32: 12880063 | B32: f05e503a-4a90-4cc8-9d25-956cdb424862 | D32: 11129 | E32: Vodacom Funeral Upsell Jan 26 | G32: MONICA | H32: SEPOGOANE | J32: TDN | K32: Temporary Disconnected Number | L32: 38 | M32: 2026-06-29 13:48:43 | N32: system | O32: 2026-01-14 13:10:31 | P32: 2026-01-14 13:10:31 | Y32: 27828612205
A33: 12880036 | B33: eac678e9-fbb4-4ebc-82e1-bc81c786b5e7 | D33: 11129 | E33: Vodacom Funeral Upsell Jan 26 | G33: ANNAH | H33: SEBICO | J33: ADC | K33: Auto Dial Disconnected | L33: 38 | M33: 2026-06-29 13:48:42 | N33: system | O33: 2026-01-14 13:10:31 | P33: 2026-01-14 13:10:31 | Y33: 27765276009
A34: 12879903 | B34: 64cd0dbc-3208-42ce-90d0-b07da3316c42 | D34: 11129 | E34: Vodacom Funeral Upsell Jan 26 | G34: WANDA | H34: MPHAYISE | J34: AA | K34: Answering Machine Autodial | L34: 38 | M34: 2026-06-29 13:48:14 | N34: system | O34: 2026-01-14 13:10:31 | P34: 2026-01-14 13:10:31 | Y34: 27792959566
A35: 12880686 | B35: 4eee5bc2-05f8-49cc-bafe-5984538de31b | D35: 11129 | E35: Vodacom Funeral Upsell Jan 26 | G35: MANTWA JULIA | H35: MALULEKE | J35: ADC | K35: Auto Dial Disconnected | L35: 38 | M35: 2026-06-29 13:48:14 | N35: system | O35: 2026-01-14 13:10:31 | P35: 2026-01-14 13:10:31 | X35: thloaelem@gmail.com | Y35: 27713694538
A36: 12882276 | B36: c255ab9e-1517-4511-b1a5-c301aed30c79 | D36: 11129 | E36: Vodacom Funeral Upsell Jan 26 | G36: zizipho | H36: sopiseks | J36: AA | K36: Answering Machine Autodial | L36: 38 | M36: 2026-06-29 13:48:10 | N36: system | O36: 2026-01-15 07:16:00 | P36: 2026-01-15 07:16:00 | X36: ziziphosopiseka58@gmail.com | Y36: 27717601298
A37: 12882216 | B37: cffcc0f8-fe0c-4f21-8e61-4ff9307464e2 | D37: 11129 | E37: Vodacom Funeral Upsell Jan 26 | G37: ITEBOGENG | H37: MOCUMI | J37: ADC | K37: Auto Dial Disconnected | L37: 38 | M37: 2026-06-29 13:48:10 | N37: system | O37: 2026-01-15 07:16:00 | P37: 2026-01-15 07:16:00 | Y37: 27715918845
A38: 12882270 | B38: c2e2553b-bd6d-4ad5-865e-21f9e100a064 | D38: 11129 | E38: Vodacom Funeral Upsell Jan 26 | G38: Lindokuhle | H38: Magade | J38: AA | K38: Answering Machine Autodial | L38: 38 | M38: 2026-06-29 13:48:08 | N38: system | O38: 2026-01-15 07:16:00 | P38: 2026-01-15 07:16:00 | X38: Kuhlelindom@gmail.com | Y38: 27608216909
A39: 12882274 | B39: 24db646e-c508-4f03-8e0b-450016bf1865 | D39: 11129 | E39: Vodacom Funeral Upsell Jan 26 | G39: ZOTHILE | H39: BIYELA | J39: AA | K39: Answering Machine Autodial | L39: 38 | M39: 2026-06-29 13:48:08 | N39: system | O39: 2026-01-15 07:16:00 | P39: 2026-01-15 07:16:00 | Y39: 27714084193
A40: 12882333 | B40: 961bd920-6549-41d0-a689-6666f8f07f6e | D40: 11129 | E40: Vodacom Funeral Upsell Jan 26 | G40: GAOEDIWE EPHRAIM | H40: BOTLHOKWANE | J40: AE | K40: Auto Engaged | L40: 38 | M40: 2026-06-29 13:48:07 | N40: system | O40: 2026-01-15 07:16:00 | P40: 2026-01-15 07:16:00 | X40: kvpowersupplyandinstallation@gmail.com | Y40: 27764645770
A41: 12882335 | B41: cb87fccf-4265-48a5-8747-7fb44b790128 | D41: 11129 | E41: Vodacom Funeral Upsell Jan 26 | G41: ANELE | H41: LUVALO | J41: AA | K41: Answering Machine Autodial | L41: 38 | M41: 2026-06-29 13:48:07 | N41: system | O41: 2026-01-15 07:16:00 | P41: 2026-01-15 07:16:00 | Y41: 27790214333
A42: 12882347 | B42: 81783c9f-71d3-4994-b538-000d1b8501b6 | D42: 11129 | E42: Vodacom Funeral Upsell Jan 26 | G42: NKOSINATHI | H42: MTHEMBU | J42: AE | K42: Auto Engaged | L42: 38 | M42: 2026-06-29 13:48:07 | N42: system | O42: 2026-01-15 07:16:00 | P42: 2026-01-15 07:16:00 | Y42: 27720895065
A43: 12882386 | B43: 909e33b6-2495-416d-b3a5-77c730093cae | D43: 11129 | E43: Vodacom Funeral Upsell Jan 26 | G43: Pride | H43: Gama | J43: CCB | K43: Call Dropped | L43: 38 | M43: 2026-06-29 13:48:01 | N43: Karabo Mpinga | O43: 2026-01-15 07:16:00 | P43: 2026-01-15 07:16:00 | X43: pridegama20@gmail.com | Y43: 27764678417
A44: 12882434 | B44: f38bd238-c658-454a-b0e9-dad20f56b706 | D44: 11129 | E44: Vodacom Funeral Upsell Jan 26 | G44: Skhosi | H44: Gloube | J44: AA | K44: Answering Machine Autodial | L44: 38 | M44: 2026-06-29 13:47:51 | N44: system | O44: 2026-01-15 07:16:00 | P44: 2026-01-15 07:16:00 | X44: bongiwenkwali11@gmail.com | Y44: 27636672285
A45: 12882390 | B45: 5a172f6e-bf00-4291-9d97-384165ffef39 | D45: 11129 | E45: Vodacom Funeral Upsell Jan 26 | G45: NOSIPHO | H45: NGIDI | J45: AA | K45: Answering Machine Autodial | L45: 38 | M45: 2026-06-29 13:47:51 | N45: system | O45: 2026-01-15 07:16:00 | P45: 2026-01-15 07:16:00 | Y45: 27609091376
A46: 12882426 | B46: 47f66693-c3a0-4c7c-8d63-97dc56c5c848 | D46: 11129 | E46: Vodacom Funeral Upsell Jan 26 | G46: Bradon | H46: sibiya | J46: AA | K46: Answering Machine Autodial | L46: 38 | M46: 2026-06-29 13:47:50 | N46: system | O46: 2026-01-15 07:16:00 | P46: 2026-01-15 07:16:00 | X46: sibiyabradon@gmail.com | Y46: 27791114323
A47: 12882456 | B47: 96e23a4e-6ff7-4890-82de-9497066fbbc2 | D47: 11129 | E47: Vodacom Funeral Upsell Jan 26 | G47: hope | H47: maebela | J47: AA | K47: Answering Machine Autodial | L47: 38 | M47: 2026-06-29 13:47:50 | N47: system | O47: 2026-01-15 07:16:00 | P47: 2026-01-15 07:16:00 | X47: maebelahope35@gmail.com | Y47: 27764195384
A48: 12882402 | B48: 97aa6d21-300b-42a6-abaf-197026fd5e46 | D48: 11129 | E48: Vodacom Funeral Upsell Jan 26 | G48: Jamey | H48: Fraser | J48: AA | K48: Answering Machine Autodial | L48: 38 | M48: 2026-06-29 13:47:50 | N48: system | O48: 2026-01-15 07:16:00 | P48: 2026-01-15 07:16:00 | X48: jameyl.fraser@gmail.com | Y48: 27724086499
A49: 12882407 | B49: db2df807-0205-4e8e-82d4-ec6fb9a78002 | D49: 11129 | E49: Vodacom Funeral Upsell Jan 26 | G49: MORONGWA | H49: DUBE | J49: AA | K49: Answering Machine Autodial | L49: 38 | M49: 2026-06-29 13:47:50 | N49: system | O49: 2026-01-15 07:16:00 | P49: 2026-01-15 07:16:00 | Y49: 27794823545
A50: 12882477 | B50: 8c105bbe-e260-47df-a162-1c5893ef9c71 | D50: 11129 | E50: Vodacom Funeral Upsell Jan 26 | G50: JANINE | H50: BRITZ | J50: NA | K50: No Answer Autodial | L50: 38 | M50: 2026-06-29 13:47:28 | N50: system | O50: 2026-01-15 07:16:00 | P50: 2026-01-15 07:16:00 | Y50: 27765716593
A51: 12882505 | B51: 644395f7-f769-4d5a-a579-9f52f63e57af | D51: 11129 | E51: Vodacom Funeral Upsell Jan 26 | G51: Zukisa | H51: Zukisa | J51: NA | K51: No Answer Autodial | L51: 38 | M51: 2026-06-29 13:47:27 | N51: system | O51: 2026-01-15 07:16:00 | P51: 2026-01-15 07:16:00 | X51: zukisamjanyelwa@gmail.com | Y51: 27790386789
A52: 12882512 | B52: 05f798bf-49fb-4285-864c-e35c5d2d8483 | D52: 11129 | E52: Vodacom Funeral Upsell Jan 26 | G52: Solomon | H52: Solomon | J52: AE | K52: Auto Engaged | L52: 38 | M52: 2026-06-29 13:47:25 | N52: system | O52: 2026-01-15 07:16:00 | P52: 2026-01-15 07:16:00 | X52: sollymona6@gmail.com | Y52: 27793356367
A53: 12882514 | B53: de586f4f-bc89-4d74-bb2c-6ac4307c71bd | D53: 11129 | E53: Vodacom Funeral Upsell Jan 26 | G53: PATRICIA | H53: GALO | J53: NA | K53: No Answer Autodial | L53: 38 | M53: 2026-06-29 13:47:25 | N53: system | O53: 2026-01-15 07:16:00 | P53: 2026-01-15 07:16:00 | Y53: 27764593671
A54: 12882523 | B54: 7ca4f7c5-c629-4483-9262-5fc0a83902bb | D54: 11129 | E54: Vodacom Funeral Upsell Jan 26 | G54: Nondumiso | H54: Lubisi | J54: NA | K54: No Answer Autodial | L54: 38 | M54: 2026-06-29 13:47:23 | N54: system | O54: 2026-01-15 07:16:00 | P54: 2026-01-15 07:16:00 | X54: ndumylubisi11@gmail.com | Y54: 27791439674
A55: 12882517 | B55: defeafe6-b6c5-4c0a-a2d9-c7879996b3c0 | D55: 11129 | E55: Vodacom Funeral Upsell Jan 26 | G55: martha | H55: ngobeni | J55: A | K55: Answering Machine | L55: 38 | M55: 2026-06-29 13:47:23 | N55: Portia Mashele | O55: 2026-01-15 07:16:00 | P55: 2026-01-15 07:16:00 | X55: marthampho233@gmail.com | Y55: 27796719109
A56: 12881950 | B56: bee01ab1-d17a-4520-b3b7-fba551e29abc | D56: 11129 | E56: Vodacom Funeral Upsell Jan 26 | G56: BENNY | H56: PITSO | J56: ADC | K56: Auto Dial Disconnected | L56: 38 | M56: 2026-06-29 13:47:22 | N56: system | O56: 2026-01-15 07:16:00 | P56: 2026-01-15 07:16:00 | Y56: 27648671913
A57: 12881899 | B57: eb7a14e2-d482-4738-8f99-06597a19697c | D57: 11129 | E57: Vodacom Funeral Upsell Jan 26 | G57: DOLPH MUNTU | H57: MBUYANE | J57: CU | K57: Client Hung Up | L57: 38 | M57: 2026-06-29 13:47:22 | N57: Kelebogile Chelechele | O57: 2026-01-15 07:16:00 | P57: 2026-01-15 07:16:00 | X57: dolphmuntu0@gmail.com | Y57: 27712702377
A58: 12881907 | B58: 8023500f-7544-4164-9485-55878bc13c3b | D58: 11129 | E58: Vodacom Funeral Upsell Jan 26 | G58: Asanda | H58: Ngxaki | J58: NA | K58: No Answer Autodial | L58: 38 | M58: 2026-06-29 13:47:22 | N58: system | O58: 2026-01-15 07:16:00 | P58: 2026-01-15 07:16:00 | X58: angxaki@gmail.com | Y58: 27724834676
A59: 12882516 | B59: df68aecf-fe94-4431-8556-e748d7059341 | D59: 11129 | E59: Vodacom Funeral Upsell Jan 26 | G59: ZAKARIA | H59: MOKOENA | J59: AA | K59: Answering Machine Autodial | L59: 38 | M59: 2026-06-29 13:47:22 | N59: system | O59: 2026-01-15 07:16:00 | P59: 2026-01-15 07:16:00 | Y59: 27761955890
A60: 12882014 | B60: 1af162b9-094f-43bd-b177-f329383e55dc | D60: 11129 | E60: Vodacom Funeral Upsell Jan 26 | G60: Solomzi | H60: Tofile | J60: AA | K60: Answering Machine Autodial | L60: 38 | M60: 2026-06-29 13:47:21 | N60: system | O60: 2026-01-15 07:16:00 | P60: 2026-01-15 07:16:00 | X60: sollytofile1991@gmail.com | Y60: 27715968725
A61: 12882034 | B61: a5561636-94d6-496a-8002-fec8050194b8 | D61: 11129 | E61: Vodacom Funeral Upsell Jan 26 | G61: PETRA | H61: SLAAI | J61: AA | K61: Answering Machine Autodial | L61: 38 | M61: 2026-06-29 13:47:20 | N61: system | O61: 2026-01-15 07:16:00 | P61: 2026-01-15 07:16:00 | Y61: 27675479479
A62: 12882043 | B62: cd00df74-f287-484b-9506-d69dea33256e | D62: 11129 | E62: Vodacom Funeral Upsell Jan 26 | G62: MARIA | H62: MALABELA | J62: NA | K62: No Answer Autodial | L62: 38 | M62: 2026-06-29 13:47:18 | N62: system | O62: 2026-01-15 07:16:00 | P62: 2026-01-15 07:16:00 | Y62: 27824797807
A63: 12882215 | B63: c00a0d8b-417f-46da-b4da-b7e637431fc0 | D63: 11129 | E63: Vodacom Funeral Upsell Jan 26 | G63: KHANYISANI REVIVE | H63: MAJOZI | J63: AE | K63: Auto Engaged | L63: 38 | M63: 2026-06-29 13:47:17 | N63: system | O63: 2026-01-15 07:16:00 | P63: 2026-01-15 07:16:00 | X63: khanyisani.majozi@gmail.com | Y63: 27727078421
A64: 12882261 | B64: 5acccfaa-91d6-43ca-b7d0-ba851dcd89e9 | D64: 11129 | E64: Vodacom Funeral Upsell Jan 26 | G64: LOUWINLEY | H64: VAN WYK | J64: NA | K64: No Answer Autodial | L64: 38 | M64: 2026-06-29 13:47:16 | N64: system | O64: 2026-01-15 07:16:00 | P64: 2026-01-15 07:16:00 | X64: louwinleyvanwyk1@gmail.com | Y64: 27735202718
A65: 12885756 | B65: 84252144-aacb-4fd4-95d5-cfd01b95a232 | D65: 11129 | E65: Vodacom Funeral Upsell Jan 26 | G65: TEBOGO | H65: MOREMI | J65: AC | K65: Already Contacted | L65: 38 | M65: 2026-06-29 13:47:12 | N65: Ongeziwe Miya | O65: 2026-01-16 08:26:05 | P65: 2026-01-16 08:26:05 | X65: Tebogo123moremi@gmail.com | Y65: 27790245990
A66: 12885573 | B66: ad24f562-896c-4d55-b91a-b8cd32d1d22a | D66: 11129 | E66: Vodacom Funeral Upsell Jan 26 | G66: Kgoloro | H66: Kubyane | J66: ADC | K66: Auto Dial Disconnected | L66: 38 | M66: 2026-06-29 13:47:11 | N66: system | O66: 2026-01-16 08:26:05 | P66: 2026-01-16 08:26:05 | X66: Kgoloro002@gmail.com | Y66: 27649985919
A67: 12885579 | B67: a626a74d-6785-4c7b-b478-6c0dd1011074 | D67: 11129 | E67: Vodacom Funeral Upsell Jan 26 | G67: Nolitha | H67: Mgedu | J67: AA | K67: Answering Machine Autodial | L67: 38 | M67: 2026-06-29 13:47:11 | N67: system | O67: 2026-01-16 08:26:05 | P67: 2026-01-16 08:26:05 | X67: nolithamgedu@gmail.com | Y67: 27794780364
A68: 12892469 | B68: 2ee19557-c4fe-4bb9-b526-60461b770036 | D68: 11129 | E68: Vodacom Funeral Upsell Jan 26 | G68: DUMSANE | H68: MAGAGULA | J68: NA | K68: No Answer Autodial | L68: 38 | M68: 2026-06-29 13:47:05 | N68: system | O68: 2026-01-20 04:07:46 | P68: 2026-01-20 04:07:46 | Y68: 27761924225
A69: 12892590 | B69: 9a8798dc-988a-4bf7-93e4-a3c3a3321181 | D69: 11129 | E69: Vodacom Funeral Upsell Jan 26 | G69: pfarelo | H69: pfarelo | J69: NA | K69: No Answer Autodial | L69: 38 | M69: 2026-06-29 13:47:05 | N69: system | O69: 2026-01-20 04:07:46 | P69: 2026-01-20 04:07:46 | X69: ramuluvhanapfarelo951@gmail.com | Y69: 27792397767
A70: 12892773 | B70: faf784ba-43dc-4c77-9a25-c42b803c7742 | D70: 11129 | E70: Vodacom Funeral Upsell Jan 26 | G70: SIMANGELE | H70: MCHUNU | J70: NA | K70: No Answer Autodial | L70: 38 | M70: 2026-06-29 13:47:05 | N70: system | O70: 2026-01-20 04:07:46 | P70: 2026-01-20 04:07:46 | Y70: 27769187956
A71: 12892872 | B71: 10fbc467-f14b-4ff8-9228-cfa5ebeba203 | D71: 11129 | E71: Vodacom Funeral Upsell Jan 26 | G71: Bathabile | H71: Bathabile | J71: ADC | K71: Auto Dial Disconnected | L71: 38 | M71: 2026-06-29 13:47:05 | N71: system | O71: 2026-01-20 04:07:46 | P71: 2026-01-20 04:07:46 | X71: bawutibathabile885@gmail.com | Y71: 27791946949
A72: 12885383 | B72: 94f06fe2-eabc-4f8c-92fa-c808aab450ae | D72: 11129 | E72: Vodacom Funeral Upsell Jan 26 | G72: Teenage | H72: matenche | J72: AE | K72: Auto Engaged | L72: 38 | M72: 2026-06-29 13:47:04 | N72: system | O72: 2026-01-16 08:26:05 | P72: 2026-01-16 08:26:05 | X72: tmanautladi6@gmail.com | Y72: 27798068714
A73: 12900000 | B73: e2309ee1-9385-4727-9a92-71f40c6f3578 | D73: 11129 | E73: Vodacom Funeral Upsell Jan 26 | G73: Sheilla Sibongile | H73: Kutama | J73: AA | K73: Answering Machine Autodial | L73: 38 | M73: 2026-06-29 13:47:04 | N73: system | O73: 2026-01-16 08:26:05 | P73: 2026-01-16 08:26:05 | X73: sskutama01@gmail.com | Y73: 27828434321
A74: 12892294 | B74: 3f2142f4-b7b9-44a3-a538-aabd92a80cdc | D74: 11129 | E74: Vodacom Funeral Upsell Jan 26 | G74: BONGANI | H74: MOLOI | J74: AA | K74: Answering Machine Autodial | L74: 38 | M74: 2026-06-29 13:47:04 | N74: system | O74: 2026-01-20 04:07:46 | P74: 2026-01-20 04:07:46 | Y74: 27726726667
A75: 12892959 | B75: 46b45d8b-7005-4a49-8bd7-6e2228a348a3 | D75: 11129 | E75: Vodacom Funeral Upsell Jan 26 | G75: BONISWA | H75: DLAMINI | J75: AA | K75: Answering Machine Autodial | L75: 38 | M75: 2026-06-29 13:47:04 | N75: system | O75: 2026-01-20 04:07:46 | P75: 2026-01-20 04:07:46 | Y75: 27715446081
A76: 12892964 | B76: dc3c6bb9-a09c-4ae9-ba07-3d46769a9d7b | D76: 11129 | E76: Vodacom Funeral Upsell Jan 26 | G76: THABANG | H76: PHAKATHI | J76: ADC | K76: Auto Dial Disconnected | L76: 38 | M76: 2026-06-29 13:47:04 | N76: system | O76: 2026-01-20 04:07:46 | P76: 2026-01-20 04:07:46 | Y76: 27648320707
A77: 12893047 | B77: 4d298578-953d-4d41-b357-3c6bebb95686 | D77: 11129 | E77: Vodacom Funeral Upsell Jan 26 | G77: SIPHUMZE | H77: NGXOBONGWANA | J77: TDN | K77: Temporary Disconnected Number | L77: 38 | M77: 2026-06-29 13:47:04 | N77: system | O77: 2026-01-20 04:07:46 | P77: 2026-01-20 04:07:46 | Y77: 27772877808
A78: 12893102 | B78: cdc82986-394c-40c2-bf45-f43f891dd555 | D78: 11129 | E78: Vodacom Funeral Upsell Jan 26 | G78: Kelly | H78: Kelly | J78: AA | K78: Answering Machine Autodial | L78: 38 | M78: 2026-06-29 13:47:04 | N78: system | O78: 2026-01-20 04:07:46 | P78: 2026-01-20 04:07:46 | X78: molovod7@gmail.com | Y78: 27766164528
A79: 12893226 | B79: df064870-e653-4642-aa01-f6e3e55a313b | D79: 11129 | E79: Vodacom Funeral Upsell Jan 26 | G79: KHOLISILE | H79: SIYAYA | J79: NA | K79: No Answer Autodial | L79: 38 | M79: 2026-06-29 13:47:04 | N79: system | O79: 2026-01-20 04:07:46 | P79: 2026-01-20 04:07:46 | Y79: 27766584931
A80: 12893337 | B80: 8d725368-4091-4025-8a03-691837e3f902 | D80: 11129 | E80: Vodacom Funeral Upsell Jan 26 | G80: KANYA | H80: LWANA | J80: ADC | K80: Auto Dial Disconnected | L80: 38 | M80: 2026-06-29 13:47:04 | N80: system | O80: 2026-01-20 04:07:46 | P80: 2026-01-20 04:07:46 | Y80: 27725812295
A81: 12893434 | B81: d543bfbb-5ea3-4137-9fbc-f9c8fdcd5929 | D81: 11129 | E81: Vodacom Funeral Upsell Jan 26 | G81: MUANO | H81: MMBOI | J81: ADC | K81: Auto Dial Disconnected | L81: 38 | M81: 2026-06-29 13:47:04 | N81: system | O81: 2026-01-20 04:07:46 | P81: 2026-01-20 04:07:46 | Y81: 27827324925
A82: 12892816 | B82: 481926d7-af60-438d-b3d0-38fd076f8fca | D82: 11129 | E82: Vodacom Funeral Upsell Jan 26 | G82: CAREL | H82: ENGELBRECHT | J82: NA | K82: No Answer Autodial | L82: 38 | M82: 2026-06-29 13:47:03 | N82: system | O82: 2026-01-20 04:07:46 | P82: 2026-01-20 06:04:43 | Q82: 1221 | R82: kroondla | S82: 299 | T82: rusnterburg | Y82: 27761456886
A83: 12892903 | B83: 942f6eeb-b51d-4426-a3b7-9f1e9fe5f9fa | D83: 11129 | E83: Vodacom Funeral Upsell Jan 26 | G83: JOSHUA | H83: ROULS | J83: NA | K83: No Answer Autodial | L83: 38 | M83: 2026-06-29 13:47:00 | N83: system | O83: 2026-01-20 04:07:46 | P83: 2026-01-20 04:07:46 | Y83: 27792533073
A84: 12893811 | B84: aed54010-12f5-493f-aa75-94ac19d41950 | D84: 11129 | E84: Vodacom Funeral Upsell Jan 26 | G84: TSHEPISO | H84: MOHUBEDU | J84: AA | K84: Answering Machine Autodial | L84: 38 | M84: 2026-06-29 13:47:00 | N84: system | O84: 2026-01-20 06:37:21 | P84: 2026-01-20 06:37:21 | Y84: 27729867136
A85: 12894287 | B85: bc34f0c8-81fa-483d-af8c-882f907e8c90 | D85: 11129 | E85: Vodacom Funeral Upsell Jan 26 | G85: HARRY | H85: LEDWABA | J85: AE | K85: Auto Engaged | L85: 38 | M85: 2026-06-29 13:46:59 | N85: system | O85: 2026-01-20 06:37:21 | P85: 2026-01-20 06:37:21 | Y85: 27606577067
A86: 12894425 | B86: dc1ea96a-ffa4-4957-bc2c-2b9c292e821b | D86: 11129 | E86: Vodacom Funeral Upsell Jan 26 | G86: VUYISILE | H86: MASEKO | J86: ADC | K86: Auto Dial Disconnected | L86: 38 | M86: 2026-06-29 13:46:59 | N86: system | O86: 2026-01-20 06:37:21 | P86: 2026-01-20 06:37:21 | Y86: 27772987169
A87: 12894316 | B87: 55b9ef66-c32f-4044-8503-74c33c2ec613 | D87: 11129 | E87: Vodacom Funeral Upsell Jan 26 | G87: APHELELE | H87: SAMANE | J87: NA | K87: No Answer Autodial | L87: 38 | M87: 2026-06-29 13:46:55 | N87: system | O87: 2026-01-20 06:37:21 | P87: 2026-01-20 06:37:21 | Y87: 27824824604
A88: 12894345 | B88: 2c01f9e7-0452-417a-87cd-859f7eeeb4f1 | D88: 11129 | E88: Vodacom Funeral Upsell Jan 26 | G88: RANDALL | H88: AFRICA | J88: AA | K88: Answering Machine Autodial | L88: 38 | M88: 2026-06-29 13:46:55 | N88: system | O88: 2026-01-20 06:37:21 | P88: 2026-01-20 06:37:21 | Y88: 27663349849
A89: 12893941 | B89: 1d394b73-22f6-44e3-b134-9c90f3de3537 | D89: 11129 | E89: Vodacom Funeral Upsell Jan 26 | G89: TELLO | H89: CHOWANE | J89: NA | K89: No Answer Autodial | L89: 38 | M89: 2026-06-29 13:46:54 | N89: system | O89: 2026-01-20 06:37:21 | P89: 2026-01-20 06:37:21 | Y89: 27761166693
A90: 12894116 | B90: 400431e2-0d3b-4ab5-b6bf-1f7c13f9d309 | D90: 11129 | E90: Vodacom Funeral Upsell Jan 26 | G90: Vuyiswa | H90: Phungula | J90: ADC | K90: Auto Dial Disconnected | L90: 38 | M90: 2026-06-29 13:46:54 | N90: system | O90: 2026-01-20 06:37:21 | P90: 2026-01-20 06:37:21 | X90: Vuyiswaphungula1@gmail.com | Y90: 27727579677
A91: 12894198 | B91: 7640a87e-1ed2-4e2b-8c0d-e6a6cb1f5e06 | D91: 11129 | E91: Vodacom Funeral Upsell Jan 26 | G91: Lebogang | H91: Radebe | J91: AE | K91: Auto Engaged | L91: 38 | M91: 2026-06-29 13:46:54 | N91: system | O91: 2026-01-20 06:37:21 | P91: 2026-01-20 06:37:21 | X91: radebelebogang5@gmail.com | Y91: 27607249208
A92: 12894157 | B92: eb6a3604-86cf-4e84-a514-d844f46cb0e1 | D92: 11129 | E92: Vodacom Funeral Upsell Jan 26 | G92: amahle | H92: mfenqa | J92: NA | K92: No Answer Autodial | L92: 38 | M92: 2026-06-29 13:46:54 | N92: system | O92: 2026-01-20 06:37:21 | P92: 2026-01-20 06:37:21 | X92: mfenqaamahle@gmail.com | Y92: 27713278884
A93: 12894066 | B93: efb311b4-77fd-4b6d-ad88-cb03cb6beb41 | D93: 11129 | E93: Vodacom Funeral Upsell Jan 26 | G93: AYANDA | H93: DLAMINI | J93: AA | K93: Answering Machine Autodial | L93: 38 | M93: 2026-06-29 13:46:54 | N93: system | O93: 2026-01-20 06:37:21 | P93: 2026-01-20 06:37:21 | Y93: 27774022393
A94: 12900000 | B94: 8260e787-d017-450a-9d2a-67d289914a8a | D94: 11129 | E94: Vodacom Funeral Upsell Jan 26 | G94: Martha | H94: Martha | J94: AE | K94: Auto Engaged | L94: 38 | M94: 2026-06-29 13:46:54 | N94: system | O94: 2026-01-20 06:37:21 | P94: 2026-01-20 06:37:21 | X94: marthammatlou6@gmail.com | Y94: 27636172324
A95: 12894629 | B95: 5a23b143-6802-4290-ae5f-ecbe249ad37f | D95: 11129 | E95: Vodacom Funeral Upsell Jan 26 | G95: CLAUDE MELANO | H95: BERA | J95: AA | K95: Answering Machine Autodial | L95: 38 | M95: 2026-06-29 13:46:54 | N95: system | O95: 2026-01-20 06:37:21 | P95: 2026-01-20 06:37:21 | X95: beraclaude4@gmail.com | Y95: 27797790943
A96: 12894642 | B96: dc7bf98e-6852-45b2-acc6-b82353e55c17 | D96: 11129 | E96: Vodacom Funeral Upsell Jan 26 | G96: TIYEHO PHILLIP | H96: MOTAUNG | J96: ADC | K96: Auto Dial Disconnected | L96: 38 | M96: 2026-06-29 13:46:54 | N96: system | O96: 2026-01-20 06:37:21 | P96: 2026-01-20 06:37:21 | X96: motaungtiyeho@gmail.com | Y96: 27711049105
A97: 12894416 | B97: 2773e9e4-ef1c-4d97-b59f-d8ac80126ea7 | D97: 11129 | E97: Vodacom Funeral Upsell Jan 26 | G97: Zimkhitha | H97: Makade | J97: NA | K97: No Answer Autodial | L97: 38 | M97: 2026-06-29 13:46:53 | N97: system | O97: 2026-01-20 06:37:21 | P97: 2026-01-20 06:37:21 | X97: zimkhithamakade@gmail.com | Y97: 27827002536
A98: 12894429 | B98: b11e5da9-230c-4c0a-bfd7-444b58915a4e | D98: 11129 | E98: Vodacom Funeral Upsell Jan 26 | G98: MKWENKWEZI | H98: GAUSHE | J98: ADC | K98: Auto Dial Disconnected | L98: 38 | M98: 2026-06-29 13:46:53 | N98: system | O98: 2026-01-20 06:37:21 | P98: 2026-01-20 06:37:21 | Y98: 27673577685
A99: 12905836 | B99: 49916135-9233-4b53-b6d3-0dbb3a8e3916 | D99: 11129 | E99: Vodacom Funeral Upsell Jan 26 | G99: PRECIOUS | H99: LEHONG | J99: AE | K99: Auto Engaged | L99: 38 | M99: 2026-06-29 13:46:53 | N99: system | O99: 2026-01-21 06:21:57 | P99: 2026-01-23 11:41:18 | X99: precioulehong28@gmail.com | Y99: 27796723636
A100: 12905369 | B100: fd34f754-990d-467f-a6b0-1bd93c3e4d0a | D100: 11129 | E100: Vodacom Funeral Upsell Jan 26 | G100: Lindelani | H100: Makhanya | J100: AA | K100: Answering Machine Autodial | L100: 38 | M100: 2026-06-29 13:46:51 | N100: system | O100: 2026-01-21 06:21:57 | P100: 2026-01-21 06:21:57 | X100: makhanyalindelani1@gmail.com | Y100: 27606425942
...

Sheet Pivot
A1: Outcome Description | B1: Count
A2: Client Hung Up | B2: 3873
A3: Sale Made | B3: 2124
A4: Auto Dial Disconnected | B4: 1753
A5: Callback | B5: 1243
A6: Answering Machine Autodial | B6: 1180
A7: Not Interested | B7: 919
A8: No Answer Autodial | B8: 661
A9: Unemployed | B9: 556
A10: Auto Engaged | B10: 524
A11: Affordability | B11: 514
A12: Wrong Number | B12: 430
A13: Already Contacted | B13: 422
... A39: Grand Total | B39: 15816

Sheet Campaign Analysis
A1: Clientele Bellringer Leads Campaign Analysis
B5: Unsuccessful Contacts | C5: Lead Count | D5: Interested in Deal? | E5: Lead Count | F5: Successful Contacts | G5: Lead Count | H5: True Contacts | I5: Lead Count
B6: Answering Machine Autodial | C6: =IFERROR(VLOOKUP("Answering Machine Autodial", Pivot!$A$2:$B$38, 2, FALSE), 0) -> 0 | D6: Sale Made - Completed Mandate | E6: =IFERROR(VLOOKUP("Sale Made - Completed Mandate", Pivot!$A$2:$B$38, 2, FALSE), 0) -> 0 | F6: Already Contacted | G6: =IFERROR(VLOOKUP("Already Contacted", Pivot!$A$2:$B$38, 2, FALSE), 0) -> 0 | H6: Client Hung Up | I6: =IFERROR(VLOOKUP("Client Hung Up", Pivot!$A$2:$B$38, 2, FALSE), 0) -> 0
B7: No Answer Autodial | C7: =IFERROR(VLOOKUP("No Answer Autodial", Pivot!$A$2:$B$38, 2, FALSE), 0) -> 0 | D7: Sale Made - Pending Mandate | E7: =IFERROR(VLOOKUP("Sale Made - Pending Mandate", Pivot!$A$2:$B$38, 2, FALSE), 0) -> 0 | F7: Existing Client | G7: =IFERROR(VLOOKUP("Existing Client", Pivot!$A$2:$B$38, 2, FALSE), 0) -> 0 | H7: CallBack | I7: =IFERROR(VLOOKUP("CallBack", Pivot!$A$2:$B$38, 2, FALSE), 0) -> 0
B8: Auto Engaged | C8: =IFERROR(VLOOKUP("Auto Engaged", Pivot!$A$2:$B$38, 2, FALSE), 0) -> 0 | D8: Sale Made | E8: =IFERROR(VLOOKUP("Sale Made", Pivot!$A$2:$B$38, 2, FALSE), 0) -> 0 | F8: Unemployed | G8: =IFERROR(VLOOKUP("Unemployed", Pivot!$A$2:$B$38, 2, FALSE), 0) -> 0 | H8: Not Interested | I8: =IFERROR(VLOOKUP("Not Interested", Pivot!$A$2:$B$38, 2, FALSE), 0) -> 0
B9: Disconnected Number Auto | C9: =IFERROR(VLOOKUP("Disconnected Number Auto", Pivot!$A$2:$B$38, 2, FALSE), 0) -> 0 | D9: Tyme Bank Account Sale | E9: =IFERROR(VLOOKUP("Tyme Bank Account Sale", Pivot!$A$2:$B$38, 2, FALSE), 0) -> 0 | F9: Wrong Number | G9: =IFERROR(VLOOKUP("Wrong Number", Pivot!$A$2:$B$38, 2, FALSE), 0) -> 0 | H9: Not Interested Upfront | I9: =IFERROR(VLOOKUP("Not Interested Upfront", Pivot!$A$2:$B$38, 2, FALSE), 0) -> 0
B10: Answering Machine | C10: =IFERROR(VLOOKUP("Answering Machine", Pivot!$A$2:$B$38, 2, FALSE), 0) -> 0 | D10: QA Rework | E10: =IFERROR(VLOOKUP("QA Rework", Pivot!$A$2:$B$38, 2, FALSE), 0) -> 0 | F10: Do Not Call | G10: =IFERROR(VLOOKUP("Do Not Call", Pivot!$A$2:$B$38, 2, FALSE), 0) -> 0 | H10: Cannot Afford Premium | I10: =IFERROR(VLOOKUP("Cannot Afford Premium", Pivot!$A$2:$B$38, 2, FALSE), 0) -> 0
B11: Selected | C11: =IFERROR(VLOOKUP("Selected", Pivot!$A$2:$B$38, 2, FALSE), 0) -> 0 | F11: No Smartphones | G11: =IFERROR(VLOOKUP("No Smartphones", Pivot!$A$2:$B$38, 2, FALSE), 0) -> 0 | H11: Not interested - Pitched | I11: =IFERROR(VLOOKUP("Not interested - Pitched", Pivot!$A$2:$B$38, 2, FALSE), 0) -> 0
B12: No Answer | C12: =IFERROR(VLOOKUP("No Answer", Pivot!$A$2:$B$38, 2, FALSE), 0) -> 0 | F12: Client Deceased | G12: =IFERROR(VLOOKUP("Client Deceased", Pivot!$A$2:$B$38, 2, FALSE), 0) -> 0 | H12: Affordability | I12: =IFERROR(VLOOKUP("Affordability", Pivot!$A$2:$B$38, 2, FALSE), 0) -> 0
B13: Busy Tone | C13: =IFERROR(VLOOKUP("Busy Tone", Pivot!$A$2:$B$38, 2, FALSE), 0) -> 0 | F13: Right Party Not Available | G13: =IFERROR(VLOOKUP("Right Party Not Available", Pivot!$A$2:$B$38, 2, FALSE), 0) -> 0 | H13: Quoted Client Not Interested | I13: =IFERROR(VLOOKUP("Quoted Client Not Interested", Pivot!$A$2:$B$38, 2, FALSE), 0) -> 0
B14: Dropped | C14: =IFERROR(VLOOKUP("Dropped", Pivot!$A$2:$B$38, 2, FALSE), 0) -> 0 | F14: Client Overage Limit | G14: =IFERROR(VLOOKUP("Client Overage Limit", Pivot!$A$2:$B$38, 2, FALSE), 0) -> 0 | H14: Not interested business does not use speed point mac | I14: =IFERROR(VLOOKUP("Not interested business does not use speed point mac", Pivot!$A$2:$B$38, 2, FALSE), 0) -> 0
B15: New | C15: =IFERROR(VLOOKUP("New", Pivot!$A$2:$B$38, 2, FALSE), 0) -> 0 | F15: Language Barrier | G15: =IFERROR(VLOOKUP("Language Barrier", Pivot!$A$2:$B$38, 2, FALSE), 0) -> 0 | H15: Call Back Technical Error | I15: =IFERROR(VLOOKUP("Call Back Technical Error", Pivot!$A$2:$B$38, 2, FALSE), 0) -> 0
B16: Call Dropped | C16: =IFERROR(VLOOKUP("Call Dropped", Pivot!$A$2:$B$38, 2, FALSE), 0) -> 0 | F16: Non SA Citizen | G16: =IFERROR(VLOOKUP("Non SA Citizen", Pivot!$A$2:$B$38, 2, FALSE), 0) -> 0 | H16: Not Interested Transaction Fees | I16: =IFERROR(VLOOKUP("Not Interested Transaction Fees", Pivot!$A$2:$B$38, 2, FALSE), 0) -> 0
B17: Inbound After Hours Drop | C17: =IFERROR(VLOOKUP("Inbound After Hours Drop", Pivot!$A$2:$B$38, 2, FALSE), 0) -> 0 | F17: No Bank Account | G17: =IFERROR(VLOOKUP("No Bank Account", Pivot!$A$2:$B$38, 2, FALSE), 0) -> 0 | H17: Cannot Afford | I17: =IFERROR(VLOOKUP("Cannot Afford", Pivot!$A$2:$B$38, 2, FALSE), 0) -> 0
B18: TPS Registered Number | C18: =IFERROR(VLOOKUP("TPS Registered Number", Pivot!$A$2:$B$38, 2, FALSE), 0) -> 0 | F18: Client Underage | G18: =IFERROR(VLOOKUP("Client Underage", Pivot!$A$2:$B$38, 2, FALSE), 0) -> 0 | H18: Not Interested Household Contents | I18: =IFERROR(VLOOKUP("Not Interested Household Contents", Pivot!$A$2:$B$38, 2, FALSE), 0) -> 0
B19: Temporary Disconnected Number | C19: =IFERROR(VLOOKUP("Temporary Disconnected Number", Pivot!$A$2:$B$38, 2, FALSE), 0) -> 0 | F19: Go To The Branch | G19: =IFERROR(VLOOKUP("Go To The Branch", Pivot!$A$2:$B$38, 2, FALSE), 0) -> 0 | H19: Call Back Hold | I19: =IFERROR(VLOOKUP("Call Back Hold", Pivot!$A$2:$B$38, 2, FALSE), 0) -> 0
B20: Bad Line Quality | C20: =IFERROR(VLOOKUP("Bad Line Quality", Pivot!$A$2:$B$38, 2, FALSE), 0) -> 0 | F20: Completed | G20: =IFERROR(VLOOKUP("Completed", Pivot!$A$2:$B$38, 2, FALSE), 0) -> 0 | H20: Declined Sale | I20: =IFERROR(VLOOKUP("Declined Sale", Pivot!$A$2:$B$38, 2, FALSE), 0) -> 0
B21: Inbound Abandon | C21: =IFERROR(VLOOKUP("Inbound Abandon", Pivot!$A$2:$B$38, 2, FALSE), 0) -> 0 | F21: Cannot Afford Upfront Payment | G21: =IFERROR(VLOOKUP("Cannot Afford Upfront Payment", Pivot!$A$2:$B$38, 2, FALSE), 0) -> 0
B22: Outbound Pre-Routing Drop | C22: =IFERROR(VLOOKUP("Outbound Pre-Routing Drop", Pivot!$A$2:$B$38, 2, FALSE), 0) -> 0 | F22: Account Suspended | G22: =IFERROR(VLOOKUP("Account Suspended", Pivot!$A$2:$B$38, 2, FALSE), 0) -> 0
B23: Engaged | C23: =IFERROR(VLOOKUP("Engaged", Pivot!$A$2:$B$38, 2, FALSE), 0) -> 0 | F23: Insured at another company | G23: =IFERROR(VLOOKUP("Insured at another company", Pivot!$A$2:$B$38, 2, FALSE), 0) -> 0
B24: Disconnected | C24: =IFERROR(VLOOKUP("Disconnected", Pivot!$A$2:$B$38, 2, FALSE), 0) -> 0 | F24: Scheduled Appointment | G24: =IFERROR(VLOOKUP("Scheduled Appointment", Pivot!$A$2:$B$38, 2, FALSE), 0) -> 0
B25: CONGESTED | C25: =IFERROR(VLOOKUP("CONGESTED", Pivot!$A$2:$B$38, 2, FALSE), 0) -> 0 | F25: Refund Request | G25: =IFERROR(VLOOKUP("Refund Request", Pivot!$A$2:$B$38, 2, FALSE), 0) -> 0
B26: Flow Inbound Abandon | C26: =IFERROR(VLOOKUP("Flow Inbound Abandon", Pivot!$A$2:$B$38, 2, FALSE), 0) -> 0 | F26: Does Not Qualify | G26: =IFERROR(VLOOKUP("Does Not Qualify", Pivot!$A$2:$B$38, 2, FALSE), 0) -> 0
B27: Multiple Calls | C27: =IFERROR(VLOOKUP("Multiple Calls", Pivot!$A$2:$B$38, 2, FALSE), 0) -> 0 | F27: Does Not Have a Business | G27: =IFERROR(VLOOKUP("Does Not Have a Business", Pivot!$A$2:$B$38, 2, FALSE), 0) -> 0
B28: Missed | C28: =IFERROR(VLOOKUP("Missed", Pivot!$A$2:$B$38, 2, FALSE), 0) -> 0 | F28: Refer To Store - Doesn't want to complete online | G28: =IFERROR(VLOOKUP("Refer To Store - Doesn't want to complete online", Pivot!$A$2:$B$38, 2, FALSE), 0) -> 0
B29: Answered | C29: =IFERROR(VLOOKUP("Answered", Pivot!$A$2:$B$38, 2, FALSE), 0) -> 0 | F29: Does Not Need It Now | G29: =IFERROR(VLOOKUP("Does Not Need It Now", Pivot!$A$2:$B$38, 2, FALSE), 0) -> 0
B30: Customer drop | C30: =IFERROR(VLOOKUP("Customer drop", Pivot!$A$2:$B$38, 2, FALSE), 0) -> 0 | F30: Technical Issue | G30: =IFERROR(VLOOKUP("Technical Issue", Pivot!$A$2:$B$38, 2, FALSE), 0) -> 0
B31: Auto Dial Disconnected | C31: =IFERROR(VLOOKUP("Auto Dial Disconnected", Pivot!$A$2:$B$38, 2, FALSE), 0) -> 0 | F31: Unsuccessful Application | G31: =IFERROR(VLOOKUP("Unsuccessful Application", Pivot!$A$2:$B$38, 2, FALSE), 0) -> 0
B32: Disconnected Number Temporary | C32: =IFERROR(VLOOKUP("Disconnected Number Temporary", Pivot!$A$2:$B$38, 2, FALSE), 0) -> 0
A35: TOTAL LEADS DIALLED | B35: =SUM(C6:C31)+SUM(E6:E9) -> 0
A37: CAMPAIGN STATISTICS
A38: Successful Contacts | B38: =SUM(E6:E9) -> 0
A39: True Contacts (TC) | B39: =SUM(I6:I19) -> 0
A40: Unworkable Leads | B40: =SUM(G6:G30) -> 0
A41: Conversions | B41: =E6 -> 0
A42: Conversion Ratio (vs TC) | B42: =B38/B37 -> 0
A43: Contact Ratio | B43: =(B37+B38)/B35 -> 0
A47: Top 5 Statuses | B47: Count | C47: % Contribution
A48: Client Hung Up | B48: 3873 | C48: =B47/B35 -> 0
A49: Sale Made | B49: 2124 | C49: =B48/B35 -> 0
A50: Auto Dial Disconnected | B50: 1753 | C50: =B49/B35 -> 0
A51: Callback | B51: 1243 | C51: =B50/B35 -> 0
A52: Answering Machine Autodial | B52: 1180 | C52: =B51/B35 -> 0
