Workbook

Sheet Sheet1
A1: Campaign:
A2: Product:
A6: total leads | B6: 566
A7: unworked leads (new leads) | B7: 3
A8: succesful contacts | B8: 123
A9: true contacts | B9: 114
A10: conversion | B10: 0.01590106
A11: true sales (post qa) | B11: 9
A12: Collections
A13: Number of missed 1st Collections
A14: NTU
A15: Cancellations/Lapse
A17: contactability | B17: =B8/B6
A18: lead to sale conversion | B18: =B10/B6
A19: conversion to true sale | B19: =B11/B10
A20: true contacts to sales | B20: =B10/B9
A21: True Sale to Collections
A23: Number of Calls to Leads
A24: Number of Calls Made
A25: Number of Calls per Lead | B25: =B23/B6
A26: Number of Agents
A27: Number of Working Days
A29: Unsuccesful Contacts Dispositions
A30: Answering Machine Autodial | B30: 116
A31: No Answer Autodial | B31: 64
A32: Auto Engaged | B32: 41
A33: Answering Machine | B33: 8
A34: Temporary Disconnected Number | B34: 39
A35: Call Dropped
A36: Dropped
A37: No Answer
A38: Bad Line Quality | B38: 1
A39: Busy Tone | B39: 1
A40: Disconnected
A41: Inbound After Hours Drop | B41: 2
A42: Multiple Calls
A43: Engaged
A44: Inbound Abandon | B44: 2
A45: Outbound Pre-Routing Drop
A46: Flow Inbound Abandon
A47: Selected | B47: 8
A48: CONGESTED
A49: Completed
A50: New | B50: 3
A51: Busy
A52: Auto Dial Disconnected | B52: 101
A53: Customer drop
A54: Disconnected Number Auto
A56: Unworkable Leads Dispositions
A57: Unemployed | B57: 14
A58: Already Contacted | B58: 1
A59: Does Not Qualify | B59: 8
A60: Client Overage Limit
A61: Do not call
A62: Under Age
A63: Go To Branch
A64: Wrong number
A65: Existing Client | B65: 4
A66: Language Barrier | B66: 8
A67: Client Deceased
A68: Customer Service Transfer
A69: Unsuccessful Application | B69: 1
A70: DNQ-Income Below Threshold
A71: DNQ Quote Declined
A72: Do Not Qualify Failed Medical Question
A73: Right Party Not Available
A74: Over Age Limit | B74: 4
A75: Funeral Documents Requested
A76: Funeral Policy Query
A77: Non SA Citizen
A78: NTU Policy
A79: Not Working Cannot Afford
A80: Lead Being Called
A81: Did Not Request
A82: Does Not Need It Now
A84: true contacts | B84: 114
A85: Not Interested | B85: 29
A86: Client Hung Up | B86: 24
A87: Affordability
A88: Callback | B88: 39
A89: Not Interested Transaction Fees
A90: Company Cellphone Number
A91: Not Interested Device Cost
A92: Call Back via MS Teams
A93: Not Interested Upfront
A94: Quoted Not Interested
A95: Client Quoted Not Interested
A96: Cannot Afford | B96: 20
A97: Not Interested Premium Cost
A98: Not interested SMS
A99: Call Back Hold
A100: Declined Sale
A101: QA FAil
A102: QA Rework | B102: 2
A103: Sale Made | B103: 9
A104: Sale SMS
A105: UPSELL
A107: Unsuccesful Contacts Dispositions
A108: Answering Machine Autodial | B108: =B30/B$6
A109: No Answer Autodial | B109: =B31/B$6
...

Sheet Pivot_Data
A1: Outcome Description | B1: Count
A2: Answering Machine Autodial | B2: 116
A3: Auto Dial Disconnected | B3: 101
A4: No Answer Autodial | B4: 64
A5: Auto Engaged | B5: 41
A6: Callback | B6: 39
A7: Temporary Disconnected Number | B7: 39
A8: Not Interested | B8: 29
A9: Client Hung Up | B9: 24
A10: Cannot Afford | B10: 20
A11: Client Underage | B11: 14
A12: Unemployed | B12: 14
A13: Sale Made | B13: 9
... A30: Grand Total | B30: 566

Sheet Processed Data
A1: Contact Id | B1: Customer Id | C1: Lead Reference | D1: List Id | E1: List Name | F1: Title | G1: Firstname | H1: Lastname | I1: Gender | J1: Last Outcome | K1: Outcome Description | L1: Called Count | M1: Last Called Date | N1: Last User | O1: Created At | P1: Updated At | Q1: Address1 | R1: Address2 | S1: Address3 | T1: Town | U1: County | V1: Country | W1: Postcode | X1: Email Address | Y1: Tel1 | Z1: Tel2 | AA1: Tel3 | AB1: Tel4 | AC1: Tel5 | AD1: Tel6 | AE1: Owner Username | AF1: Security Phrase | AG1: Source Reference | AH1: Industry | AI1: Company Name | AJ1: Website | AK1: Customer Reference | AL1: Dob
A2: 14363380 | B2: f8dc77a6-fee0-4aff-9575-e837a291dda2 | D2: 30001082 | E2: ussd_funeral_leads_altitude_20260504 | G2: Enoch Hemee | H2: 27826430341 | J2: IABDN | K2: Inbound Abandon | L2: 20 | M2: 2026-06-20 11:26:10 | N2: system | O2: 2026-05-15 11:58:32 | P2: 2026-05-16 10:53:28 | Y2: 27826430341
A3: 14362976 | B3: 53740a2a-9bd0-4ac6-a638-0a12c8c6caed | D3: 30001082 | E3: ussd_funeral_leads_altitude_20260504 | J3: A | K3: Answering Machine | L3: 35 | M3: 2026-06-18 07:25:04 | N3: Gontse Monageng | O3: 2026-05-15 11:58:32 | P3: 2026-05-15 11:58:32 | Y3: 27714665093
A4: 14363191 | B4: 867745de-b899-468b-8c19-53859fd144ac | D4: 30001082 | E4: ussd_funeral_leads_altitude_20260504 | J4: A | K4: Answering Machine | L4: 16 | M4: 2026-06-18 07:19:41 | N4: Gontse Monageng | O4: 2026-05-15 11:58:32 | P4: 2026-05-15 11:58:32 | Y4: 27766744515
A5: 14363041 | B5: 2145a7f4-db1c-4a20-ab09-2144d263ebb6 | D5: 30001082 | E5: ussd_funeral_leads_altitude_20260504 | J5: LANG | K5: Language Barrier | L5: 23 | M5: 2026-06-17 07:26:06 | N5: Goitsimang Mogwasa | O5: 2026-05-15 11:58:32 | P5: 2026-05-15 11:58:32 | Y5: 27823706055
A6: 14363483 | B6: 67cd1d99-4a82-4872-8fe6-3cfad79cbf2f | D6: 30001082 | E6: ussd_funeral_leads_altitude_20260504 | J6: CU | K6: Client Hung Up | L6: 19 | M6: 2026-06-15 13:59:06 | N6: Virginia Letsatsi | O6: 2026-05-15 11:58:32 | P6: 2026-05-15 11:58:32 | Y6: 27711300245
A7: 14363179 | B7: 47ced5ae-b941-4807-82cd-4bc147f92e11 | D7: 30001082 | E7: ussd_funeral_leads_altitude_20260504 | J7: CU | K7: Client Hung Up | L7: 33 | M7: 2026-06-12 10:00:27 | N7: Goitsimang Mogwasa | O7: 2026-05-15 11:58:32 | P7: 2026-05-15 11:58:32 | Y7: 27729666409
A8: 14363311 | B8: 03bd56ff-5c5f-4449-89c5-d49a42db4b2b | D8: 30001082 | E8: ussd_funeral_leads_altitude_20260504 | H8: 8906220000000 | J8: A | K8: Answering Machine | L8: 38 | M8: 2026-06-12 09:54:48 | N8: Goitsimang Mogwasa | O8: 2026-05-15 11:58:32 | P8: 2026-05-20 10:42:16 | R8: 796441231 | Y8: 27796441231
A9: 14363258 | B9: 1447590d-0d03-4c74-929d-1dd14bd91187 | D9: 30001082 | E9: ussd_funeral_leads_altitude_20260504 | H9: 27791974610 | J9: NI | K9: Not Interested | L9: 5 | M9: 2026-06-10 10:37:04 | N9: Lebohang Mabotja | O9: 2026-05-15 11:58:32 | P9: 2026-05-15 11:58:32 | Y9: 27791974610
A10: 14363229 | B10: 723c2339-611a-45c0-943c-68f85a35fa00 | D10: 30001082 | E10: ussd_funeral_leads_altitude_20260504 | H10: 27637248420 | J10: AFTHRS | K10: Inbound After Hours Drop | L10: 31 | M10: 2026-06-08 04:26:23 | N10: system | O10: 2026-05-15 11:58:32 | P10: 2026-05-15 11:58:32 | Y10: 27637248420
A11: 14363448 | B11: 4b1fe631-1d81-4076-9d18-b0c4b47cc33f | D11: 30001082 | E11: ussd_funeral_leads_altitude_20260504 | J11: AA | K11: Answering Machine Autodial | L11: 22 | M11: 2026-06-05 11:51:04 | N11: system | O11: 2026-05-15 11:58:32 | P11: 2026-05-15 11:58:32 | Y11: 27764798912
A12: 14362986 | B12: aad7b3d4-5cb2-4a2e-8fe8-3529a26115a0 | D12: 30001082 | E12: ussd_funeral_leads_altitude_20260504 | J12: AA | K12: Answering Machine Autodial | L12: 30 | M12: 2026-06-05 09:03:22 | N12: system | O12: 2026-05-15 11:58:32 | P12: 2026-05-15 11:58:32 | Y12: 27796858996
A13: 14363454 | B13: 4babe5db-a62a-4544-b789-271e0e34c9d6 | D13: 30001082 | E13: ussd_funeral_leads_altitude_20260504 | J13: AA | K13: Answering Machine Autodial | L13: 26 | M13: 2026-06-05 08:50:57 | N13: system | O13: 2026-05-15 11:58:32 | P13: 2026-05-15 11:58:32 | Y13: 27826397051
A14: 14363131 | B14: de25cdad-e197-4ab3-9d5c-1b22ad27f5f9 | D14: 30001082 | E14: ussd_funeral_leads_altitude_20260504 | J14: A | K14: Answering Machine | L14: 31 | M14: 2026-06-03 13:54:54 | N14: Vuyiswa Nxumalo | O14: 2026-05-15 11:58:32 | P14: 2026-05-15 11:58:32 | Y14: 27795029999
A15: 14363046 | B15: 3f533fe0-ee7a-4efd-a437-b27fa260a444 | D15: 30001082 | E15: ussd_funeral_leads_altitude_20260504 | H15: 27823832770 | J15: AA | K15: Answering Machine Autodial | L15: 31 | M15: 2026-06-02 12:37:49 | N15: system | O15: 2026-05-15 11:58:32 | P15: 2026-05-15 11:58:32 | Y15: 27823832770
A16: 14363409 | B16: 1c88a8fc-958f-43bf-9135-d6c186abc801 | D16: 30001082 | E16: ussd_funeral_leads_altitude_20260504 | J16: QAVER | K16: Sale Made | L16: 24 | M16: 2026-06-02 11:31:22 | N16: Goitsimang Mogwasa | O16: 2026-05-15 11:58:32 | P16: 2026-05-15 11:58:32 | Y16: 27768009771
A17: 14363322 | B17: 94a61d81-1936-40a8-a93b-f870933354d4 | D17: 30001082 | E17: ussd_funeral_leads_altitude_20260504 | J17: AA | K17: Answering Machine Autodial | L17: 31 | M17: 2026-06-02 07:58:43 | N17: system | O17: 2026-05-15 11:58:32 | P17: 2026-05-15 11:58:32 | Y17: 27606249684
A18: 14363007 | B18: 519d2868-c2db-4692-a195-b022b95174b6 | D18: 30001082 | E18: ussd_funeral_leads_altitude_20260504 | J18: AA | K18: Answering Machine Autodial | L18: 31 | M18: 2026-06-02 07:58:37 | N18: system | O18: 2026-05-15 11:58:32 | P18: 2026-05-15 11:58:32 | Y18: 27606532434
A19: 14363183 | B19: da0ed660-feb7-4c0d-ad76-85c873abb7b9 | D19: 30001082 | E19: ussd_funeral_leads_altitude_20260504 | J19: CU | K19: Client Hung Up | L19: 31 | M19: 2026-06-02 07:58:31 | N19: Tebogo Chauke | O19: 2026-05-15 11:58:32 | P19: 2026-05-15 11:58:32 | Y19: 27728707616
A20: 14363006 | B20: 48227000-bcac-41e9-89ca-46e62daa73e9 | D20: 30001082 | E20: ussd_funeral_leads_altitude_20260504 | H20: 27723547580 | J20: CBACK | K20: Callback | L20: 31 | M20: 2026-06-01 13:21:22 | N20: Tebogo Chauke | O20: 2026-05-15 11:58:32 | P20: 2026-05-15 11:58:32 | Y20: 27723547580
A21: 14363090 | B21: f13dcbc5-de8d-43e0-af69-971ab6d22552 | D21: 30001082 | E21: ussd_funeral_leads_altitude_20260504 | H21: 27763421778 | J21: AA | K21: Answering Machine Autodial | L21: 31 | M21: 2026-06-01 13:21:22 | N21: system | O21: 2026-05-15 11:58:32 | P21: 2026-05-15 11:58:32 | Y21: 27763421778
A22: 14362974 | B22: f7a8341a-a6d0-4a52-91e8-e14efc70aa84 | D22: 30001082 | E22: ussd_funeral_leads_altitude_20260504 | J22: NA | K22: No Answer Autodial | L22: 31 | M22: 2026-06-01 08:25:12 | N22: system | O22: 2026-05-15 11:58:32 | P22: 2026-05-15 11:58:32 | Y22: 27764560946
A23: 14363359 | B23: 83df562b-0215-4ae6-94ed-8e221e176b51 | D23: 30001082 | E23: ussd_funeral_leads_altitude_20260504 | J23: CBACK | K23: Callback | L23: 31 | M23: 2026-06-01 08:25:06 | N23: Gontse Monageng | O23: 2026-05-15 11:58:32 | P23: 2026-05-15 11:58:32 | Y23: 27636700419
A24: 14363003 | B24: 9e72f715-3430-48dc-b4f4-b2a88c91cf60 | D24: 30001082 | E24: ussd_funeral_leads_altitude_20260504 | J24: AA | K24: Answering Machine Autodial | L24: 31 | M24: 2026-06-01 08:25:05 | N24: system | O24: 2026-05-15 11:58:32 | P24: 2026-05-15 11:58:32 | Y24: 27760338225
A25: 14363224 | B25: a629beda-a299-4a64-8da2-098fa42cf05b | D25: 30001082 | E25: ussd_funeral_leads_altitude_20260504 | H25: 27729464503 | J25: AFTHRS | K25: Inbound After Hours Drop | L25: 31 | M25: 2026-05-31 19:05:32 | N25: system | O25: 2026-05-15 11:58:32 | P25: 2026-05-15 11:58:32 | Y25: 27729464503
A26: 14363408 | B26: f1d3d2f9-ecee-458c-ab29-7aa3579cb40d | D26: 30001082 | E26: ussd_funeral_leads_altitude_20260504 | J26: AA | K26: Answering Machine Autodial | L26: 31 | M26: 2026-05-30 08:39:15 | N26: system | O26: 2026-05-15 11:58:32 | P26: 2026-05-15 11:58:32 | Y26: 27727907316
A27: 14363404 | B27: 3dc21dac-8c36-4d71-970c-624d73b7cf4e | D27: 30001082 | E27: ussd_funeral_leads_altitude_20260504 | J27: AA | K27: Answering Machine Autodial | L27: 31 | M27: 2026-05-30 08:39:13 | N27: system | O27: 2026-05-15 11:58:32 | P27: 2026-05-15 11:58:32 | Y27: 27715614241
A28: 14363405 | B28: abcc32dd-6d06-4514-b0f4-c1b279b2e1e9 | D28: 30001082 | E28: ussd_funeral_leads_altitude_20260504 | J28: AA | K28: Answering Machine Autodial | L28: 31 | M28: 2026-05-30 08:39:13 | N28: system | O28: 2026-05-15 11:58:32 | P28: 2026-05-15 11:58:32 | Y28: 27829307613
A29: 14363383 | B29: c68caed1-58f6-47b8-a771-4cacf688fa23 | D29: 30001082 | E29: ussd_funeral_leads_altitude_20260504 | J29: AA | K29: Answering Machine Autodial | L29: 31 | M29: 2026-05-30 08:39:12 | N29: system | O29: 2026-05-15 11:58:32 | P29: 2026-05-15 11:58:32 | Y29: 27715049962
A30: 14363394 | B30: 130b0a21-a1ba-4bc5-845f-78dabf62fca8 | D30: 30001082 | E30: ussd_funeral_leads_altitude_20260504 | J30: AA | K30: Answering Machine Autodial | L30: 31 | M30: 2026-05-30 08:39:12 | N30: system | O30: 2026-05-15 11:58:32 | P30: 2026-05-15 11:58:32 | Y30: 27664924623
A31: 14363403 | B31: 8f04b76b-be2a-431c-908d-5bd372b1c1b1 | D31: 30001082 | E31: ussd_funeral_leads_altitude_20260504 | J31: AA | K31: Answering Machine Autodial | L31: 31 | M31: 2026-05-30 08:39:12 | N31: system | O31: 2026-05-15 11:58:32 | P31: 2026-05-15 11:58:32 | Y31: 27721580339
A32: 14363217 | B32: 10ba4618-b33c-487c-a6db-ffa8e241c963 | D32: 30001082 | E32: ussd_funeral_leads_altitude_20260504 | J32: AA | K32: Answering Machine Autodial | L32: 31 | M32: 2026-05-30 08:39:11 | N32: system | O32: 2026-05-15 11:58:32 | P32: 2026-05-15 11:58:32 | Y32: 27716052740
A33: 14363213 | B33: 0f565b57-609d-4dc3-94a7-2d3e3d08358d | D33: 30001082 | E33: ussd_funeral_leads_altitude_20260504 | J33: ADC | K33: Auto Dial Disconnected | L33: 31 | M33: 2026-05-30 08:39:10 | N33: system | O33: 2026-05-15 11:58:32 | P33: 2026-05-15 11:58:32 | Y33: 27765060159
A34: 14400000 | B34: e2989590-05c8-4d11-8454-7300ef82f28d | D34: 30001082 | E34: ussd_funeral_leads_altitude_20260504 | J34: AA | K34: Answering Machine Autodial | L34: 31 | M34: 2026-05-30 08:39:10 | N34: system | O34: 2026-05-15 11:58:32 | P34: 2026-05-15 11:58:32 | Y34: 27772916810
A35: 14363208 | B35: e39e3196-1c45-4f67-9985-cb7bfcbf5246 | D35: 30001082 | E35: ussd_funeral_leads_altitude_20260504 | J35: AA | K35: Answering Machine Autodial | L35: 31 | M35: 2026-05-30 08:39:10 | N35: system | O35: 2026-05-15 11:58:32 | P35: 2026-05-15 11:58:32 | Y35: 27673149020
A36: 14363152 | B36: 1a518f6c-051c-4629-a28f-7035ce8d5778 | D36: 30001082 | E36: ussd_funeral_leads_altitude_20260504 | J36: NA | K36: No Answer Autodial | L36: 31 | M36: 2026-05-30 08:39:08 | N36: system | O36: 2026-05-15 11:58:32 | P36: 2026-05-15 11:58:32 | Y36: 27764707110
A37: 14362962 | B37: 62000052-c2df-429b-be13-886ad1f0175a | D37: 30001082 | E37: ussd_funeral_leads_altitude_20260504 | J37: AA | K37: Answering Machine Autodial | L37: 31 | M37: 2026-05-30 08:39:07 | N37: system | O37: 2026-05-15 11:58:32 | P37: 2026-05-15 11:58:32 | Y37: 27720512816
... A54: 14362938 | B54: e13a03b0-3cf1-4b40-ab72-ce44618f7565 | D54: 30001082 | E54: ussd_funeral_leads_altitude_20260504 | J54: AA | K54: Answering Machine Autodial | L54: 31 | M54: 2026-05-30 08:38:34 | N54: system | O54: 2026-05-15 11:58:32 | P54: 2026-05-15 11:58:32 | Y54: 27646018700
A55: 14362935 | B55: 686f99ec-b253-4b4d-8cf4-dc359394f5b8 | D55: 30001082 | E55: ussd_funeral_leads_altitude_20260504 | H55: 27649612807 | J55: A | K55: Answering Machine | L55: 31 | M55: 2026-05-30 08:38:28 | N55: Vuyiswa Nxumalo | O55: 2026-05-15 11:58:32 | P55: 2026-05-15 11:58:32 | Y55: 27649612807
A56: 14362991 | B56: 99c4ae80-8619-458b-9f11-f0ec367a47de | D56: 30001082 | E56: ussd_funeral_leads_altitude_20260504 | J56: AA | K56: Answering Machine Autodial | L56: 31 | M56: 2026-05-30 08:38:22 | N56: system | O56: 2026-05-15 11:58:32 | P56: 2026-05-15 11:58:32 | Y56: 27761913959
A57: 14363000 | B57: 18cd151f-b098-4909-91b7-d9041e744711 | D57: 30001082 | E57: ussd_funeral_leads_altitude_20260504 | J57: BLQ | K57: Bad Line Quality | L57: 31 | M57: 2026-05-30 08:38:22 | N57: Gontse Monageng | O57: 2026-05-15 11:58:32 | P57: 2026-05-15 11:58:32 | Y57: 27763356245
A58: 14362982 | B58: 812ed7c4-c6f8-4f4b-9067-4d1568cbda7c | D58: 30001082 | E58: ussd_funeral_leads_altitude_20260504 | J58: AA | K58: Answering Machine Autodial | L58: 31 | M58: 2026-05-30 08:38:18 | N58: system | O58: 2026-05-15 11:58:32 | P58: 2026-05-15 11:58:32 | Y58: 27609252901
A59: 14363114 | B59: b669a103-338c-4ce3-a403-2cf1ef2610a3 | D59: 30001082 | E59: ussd_funeral_leads_altitude_20260504 | J59: NA | K59: No Answer Autodial | L59: 31 | M59: 2026-05-30 08:38:17 | N59: system | O59: 2026-05-15 11:58:32 | P59: 2026-05-15 11:58:32 | Y59: 27791677711
A60: 14400000 | B60: 0e46072a-0c48-44fb-bd32-7b123bacbb6f | D60: 30001082 | E60: ussd_funeral_leads_altitude_20260504 | J60: AA | K60: Answering Machine Autodial | L60: 31 | M60: 2026-05-30 08:38:16 | N60: system | O60: 2026-05-15 11:58:32 | P60: 2026-05-15 11:58:32 | Y60: 27660384894
A61: 14363016 | B61: 0a9ddc21-e279-4c97-9db8-78a127d6f3fc | D61: 30001082 | E61: ussd_funeral_leads_altitude_20260504 | H61: 27714067469 | J61: NA | K61: No Answer Autodial | L61: 31 | M61: 2026-05-30 08:38:14 | N61: system | O61: 2026-05-15 11:58:32 | P61: 2026-05-15 11:58:32 | Y61: 27714067469
A62: 14363012 | B62: 1c7a0bef-9dcf-4326-a42c-e014e051df78 | D62: 30001082 | E62: ussd_funeral_leads_altitude_20260504 | J62: CU | K62: Client Hung Up | L62: 31 | M62: 2026-05-30 08:38:13 | N62: Goitsimang Mogwasa | O62: 2026-05-15 11:58:32 | P62: 2026-05-15 11:58:32 | Y62: 27827114658
A63: 14362946 | B63: 9473f9ea-c2f2-493d-b306-74278253bd6e | D63: 30001082 | E63: ussd_funeral_leads_altitude_20260504 | J63: AA | K63: Answering Machine Autodial | L63: 31 | M63: 2026-05-30 08:38:13 | N63: system | O63: 2026-05-15 11:58:32 | P63: 2026-05-15 11:58:32 | Y63: 27767293206
A64: 14363358 | B64: ac6d89b1-774e-4a72-9a40-143823d25206 | D64: 30001082 | E64: ussd_funeral_leads_altitude_20260504 | J64: AA | K64: Answering Machine Autodial | L64: 31 | M64: 2026-05-30 08:38:12 | N64: system | O64: 2026-05-15 11:58:32 | P64: 2026-05-15 11:58:32 | Y64: 27727287950
A65: 14363368 | B65: 00febfad-385b-4208-a279-08222c572848 | D65: 30001082 | E65: ussd_funeral_leads_altitude_20260504 | J65: NA | K65: No Answer Autodial | L65: 31 | M65: 2026-05-30 08:38:12 | N65: system | O65: 2026-05-15 11:58:32 | P65: 2026-05-15 11:58:32 | Y65: 27797923430
A66: 14363371 | B66: 2d17e892-0c54-4795-9a57-95f6b4341503 | D66: 30001082 | E66: ussd_funeral_leads_altitude_20260504 | J66: AA | K66: Answering Machine Autodial | L66: 31 | M66: 2026-05-30 08:38:12 | N66: system | O66: 2026-05-15 11:58:32 | P66: 2026-05-15 11:58:32 | Y66: 27762251327
A67: 14363337 | B67: dcaa5ab7-d3ae-48e2-beaf-2a8db51ba040 | D67: 30001082 | E67: ussd_funeral_leads_altitude_20260504 | J67: AA | K67: Answering Machine Autodial | L67: 31 | M67: 2026-05-30 08:38:11 | N67: system | O67: 2026-05-15 11:58:32 | P67: 2026-05-15 11:58:32 | Y67: 27725708045
A68: 14363348 | B68: 853f2ea1-2bef-4161-8bfb-3fdcc5fb37b5 | D68: 30001082 | E68: ussd_funeral_leads_altitude_20260504 | J68: NA | K68: No Answer Autodial | L68: 31 | M68: 2026-05-30 08:38:11 | N68: system | O68: 2026-05-15 11:58:32 | P68: 2026-05-15 11:58:32 | Y68: 27711298441
A69: 14363349 | B69: 3cc299e5-b0c3-42e5-ad79-1e925af23c74 | D69: 30001082 | E69: ussd_funeral_leads_altitude_20260504 | J69: NA | K69: No Answer Autodial | L69: 31 | M69: 2026-05-30 08:38:11 | N69: system | O69: 2026-05-15 11:58:32 | P69: 2026-05-15 11:58:32 | Y69: 27646919861
A70: 14363350 | B70: f174464d-4199-491c-a6e3-662f017e6cc6 | D70: 30001082 | E70: ussd_funeral_leads_altitude_20260504 | H70: 27661638169 | J70: ADC | K70: Auto Dial Disconnected | L70: 31 | M70: 2026-05-30 08:38:11 | N70: system | O70: 2026-05-15 11:58:32 | P70: 2026-05-15 11:58:32 | Y70: 27661638169
A71: 14363353 | B71: 28cbb737-04cc-4904-9c5f-e68805cba5e6 | D71: 30001082 | E71: ussd_funeral_leads_altitude_20260504 | J71: AA | K71: Answering Machine Autodial | L71: 31 | M71: 2026-05-30 08:38:11 | N71: system | O71: 2026-05-15 11:58:32 | P71: 2026-05-15 11:58:32 | Y71: 27769388910
A72: 14363328 | B72: 4949d1c5-25f5-4f17-90ef-09c3303a4110 | D72: 30001082 | E72: ussd_funeral_leads_altitude_20260504 | J72: NA | K72: No Answer Autodial | L72: 31 | M72: 2026-05-30 08:38:06 | N72: system | O72: 2026-05-15 11:58:32 | P72: 2026-05-15 11:58:32 | Y72: 27637185872
A73: 14363334 | B73: 4c1d6dff-8829-4926-92f7-f1c7adb16077 | D73: 30001082 | E73: ussd_funeral_leads_altitude_20260504 | J73: AA | K73: Answering Machine Autodial | L73: 31 | M73: 2026-05-30 08:38:06 | N73: system | O73: 2026-05-15 11:58:32 | P73: 2026-05-15 11:58:32 | Y73: 27716941870
A74: 14363319 | B74: 90669d99-a895-40f3-9e00-694c957ce4a3 | D74: 30001082 | E74: ussd_funeral_leads_altitude_20260504 | J74: AA | K74: Answering Machine Autodial | L74: 31 | M74: 2026-05-30 08:38:05 | N74: system | O74: 2026-05-15 11:58:32 | P74: 2026-05-15 11:58:32 | Y74: 27728975929
A75: 14363288 | B75: c23231ae-ded3-41ff-b9ff-040f1ffcd8e2 | D75: 30001082 | E75: ussd_funeral_leads_altitude_20260504 | J75: AA | K75: Answering Machine Autodial | L75: 31 | M75: 2026-05-30 08:38:05 | N75: system | O75: 2026-05-15 11:58:32 | P75: 2026-05-15 11:58:32 | Y75: 27774784951
A76: 14363293 | B76: 7a96f913-e56e-4424-8821-1bc49d233b7b | D76: 30001082 | E76: ussd_funeral_leads_altitude_20260504 | J76: NA | K76: No Answer Autodial | L76: 31 | M76: 2026-05-30 08:38:05 | N76: system | O76: 2026-05-15 11:58:32 | P76: 2026-05-15 11:58:32 | Y76: 27790920484
A77: 14363299 | B77: 27a45de9-c6b0-4640-97f6-58c624bce843 | D77: 30001082 | E77: ussd_funeral_leads_altitude_20260504 | H77: 27772926571 | J77: CU | K77: Client Hung Up | L77: 31 | M77: 2026-05-30 08:38:05 | N77: Dimakatso Nkomo | O77: 2026-05-15 11:58:32 | P77: 2026-05-15 11:58:32 | Y77: 27772926571
A78: 14363306 | B78: 2860747d-1ec6-4854-acc5-9da010b3a440 | D78: 30001082 | E78: ussd_funeral_leads_altitude_20260504 | J78: AA | K78: Answering Machine Autodial | L78: 31 | M78: 2026-05-30 08:38:05 | N78: system | O78: 2026-05-15 11:58:32 | P78: 2026-05-15 11:58:32 | Y78: 27675647731
A79: 14363273 | B79: fee97097-f31c-4feb-985c-345c2afea54d | D79: 30001082 | E79: ussd_funeral_leads_altitude_20260504 | J79: CU | K79: Client Hung Up | L79: 31 | M79: 2026-05-30 08:38:03 | N79: Jennifer Ngobeni | O79: 2026-05-15 11:58:32 | P79: 2026-05-15 11:58:32 | Y79: 27761667456
A80: 14363278 | B80: b64d2b9b-e207-4038-b902-3c83a546571e | D80: 30001082 | E80: ussd_funeral_leads_altitude_20260504 | J80: AE | K80: Auto Engaged | L80: 31 | M80: 2026-05-30 08:38:03 | N80: system | O80: 2026-05-15 11:58:32 | P80: 2026-05-15 11:58:32 | Y80: 27646331515
A81: 14400000 | B81: e80509f4-5a52-4b38-856a-9f34b7351aba | D81: 30001082 | E81: ussd_funeral_leads_altitude_20260504 | J81: AA | K81: Answering Machine Autodial | L81: 31 | M81: 2026-05-30 08:37:59 | N81: system | O81: 2026-05-15 11:58:32 | P81: 2026-05-15 11:58:32 | Y81: 27648290036
A82: 14363246 | B82: aec46ca9-5bfd-41ce-8949-e84c96eed32d | D82: 30001082 | E82: ussd_funeral_leads_altitude_20260504 | J82: AA | K82: Answering Machine Autodial | L82: 31 | M82: 2026-05-30 08:37:59 | N82: system | O82: 2026-05-15 11:58:32 | P82: 2026-05-15 11:58:32 | Y82: 27673446737
A83: 14363243 | B83: 4eb46838-eb31-4550-919e-cd31ccd28f17 | D83: 30001082 | E83: ussd_funeral_leads_altitude_20260504 | J83: AA | K83: Answering Machine Autodial | L83: 31 | M83: 2026-05-30 08:37:58 | N83: system | O83: 2026-05-15 11:58:32 | P83: 2026-05-15 11:58:32 | Y83: 27824593350
A84: 14363236 | B84: f979ae51-caba-420e-9afe-b017aca6ab5a | D84: 30001082 | E84: ussd_funeral_leads_altitude_20260504 | J84: AA | K84: Answering Machine Autodial | L84: 31 | M84: 2026-05-30 08:37:46 | N84: system | O84: 2026-05-15 11:58:32 | P84: 2026-05-15 11:58:32 | Y84: 27769574023
A85: 14363218 | B85: 0de872ea-ec02-4c34-9ba5-df7fb8ff34e0 | D85: 30001082 | E85: ussd_funeral_leads_altitude_20260504 | J85: AA | K85: Answering Machine Autodial | L85: 31 | M85: 2026-05-30 08:37:43 | N85: system | O85: 2026-05-15 11:58:32 | P85: 2026-05-15 11:58:32 | Y85: 27674940164
A86: 14363226 | B86: a797bda5-25e0-4343-beb5-fa104afb4c5b | D86: 30001082 | E86: ussd_funeral_leads_altitude_20260504 | J86: NA | K86: No Answer Autodial | L86: 31 | M86: 2026-05-30 08:37:43 | N86: system | O86: 2026-05-15 11:58:32 | P86: 2026-05-15 11:58:32 | Y86: 27760633408
A87: 14363257 | B87: c47e3c09-3ffd-4407-805f-7fc7bb2cb284 | D87: 30001082 | E87: ussd_funeral_leads_altitude_20260504 | J87: CU | K87: Client Hung Up | L87: 32 | M87: 2026-05-30 07:14:37 | N87: Tebogo Chauke | O87: 2026-05-15 11:58:32 | P87: 2026-05-15 11:58:32 | Y87: 27723815906
A88: 14363011 | B88: be0fea64-42f1-4708-a6e1-5d959a9dbd86 | D88: 30001082 | E88: ussd_funeral_leads_altitude_20260504 | H88: 27606656596 | J88: IABDN | K88: Inbound Abandon | L88: 31 | M88: 2026-05-29 14:35:34 | N88: system | O88: 2026-05-15 11:58:32 | P88: 2026-05-15 11:58:32 | Y88: 27606656596
A89: 14363205 | B89: 14ce8898-3969-4a11-9c5a-11b7e6a85f6e | D89: 30001082 | E89: ussd_funeral_leads_altitude_20260504 | J89: AA | K89: Answering Machine Autodial | L89: 31 | M89: 2026-05-29 12:11:24 | N89: system | O89: 2026-05-15 11:58:32 | P89: 2026-05-15 11:58:32 | Y89: 27710000052
A90: 14363476 | B90: 86b3754a-86be-4194-a87b-b4987fb0e9ef | D90: 30001082 | E90: ussd_funeral_leads_altitude_20260504 | J90: NA | K90: No Answer Autodial | L90: 31 | M90: 2026-05-29 11:42:49 | N90: system | O90: 2026-05-15 11:58:32 | P90: 2026-05-15 11:58:32 | Y90: 27763046811
A91: 14363462 | B91: b7ccc99b-2a93-4e4e-95b2-d42627707daf | D91: 30001082 | E91: ussd_funeral_leads_altitude_20260504 | J91: AA | K91: Answering Machine Autodial | L91: 31 | M91: 2026-05-29 11:42:48 | N91: system | O91: 2026-05-15 11:58:32 | P91: 2026-05-15 11:58:32 | Y91: 27726012403
A92: 14363464 | B92: 0d7c5222-4c66-4ed3-98fb-c4ea30b5e97a | D92: 30001082 | E92: ussd_funeral_leads_altitude_20260504 | J92: AA | K92: Answering Machine Autodial | L92: 31 | M92: 2026-05-29 11:42:48 | N92: system | O92: 2026-05-15 11:58:32 | P92: 2026-05-15 11:58:32 | Y92: 27649505791
A93: 14363470 | B93: 0ba18784-84fa-42a4-a402-1524d41f9390 | D93: 30001082 | E93: ussd_funeral_leads_altitude_20260504 | J93: AA | K93: Answering Machine Autodial | L93: 31 | M93: 2026-05-29 11:42:48 | N93: system | O93: 2026-05-15 11:58:32 | P93: 2026-05-15 11:58:32 | Y93: 27818374255
A94: 14363474 | B94: 4c418d49-c59b-409a-8232-94e6413e10e6 | D94: 30001082 | E94: ussd_funeral_leads_altitude_20260504 | J94: AA | K94: Answering Machine Autodial | L94: 31 | M94: 2026-05-29 11:42:48 | N94: system | O94: 2026-05-15 11:58:32 | P94: 2026-05-15 11:58:32 | Y94: 27774176145
A95: 14363487 | B95: 9c5679fb-48d3-4c55-8605-c2fcede612c5 | D95: 30001082 | E95: ussd_funeral_leads_altitude_20260504 | J95: CU | K95: Client Hung Up | L95: 31 | M95: 2026-05-29 11:42:47 | N95: Jennifer Ngobeni | O95: 2026-05-15 11:58:32 | P95: 2026-05-15 11:58:32 | Y95: 27827811734
A96: 14363457 | B96: f8254be6-6425-4b81-808c-d64ad5ee1f30 | D96: 30001082 | E96: ussd_funeral_leads_altitude_20260504 | J96: NA | K96: No Answer Autodial | L96: 31 | M96: 2026-05-29 11:42:46 | N96: system | O96: 2026-05-15 11:58:32 | P96: 2026-05-15 11:58:32 | Y96: 27674641386
A97: 14363452 | B97: 8b90dc5f-44f7-49cf-abf2-a19ae45fa756 | D97: 30001082 | E97: ussd_funeral_leads_altitude_20260504 | H97: 27649870418 | J97: AA | K97: Answering Machine Autodial | L97: 31 | M97: 2026-05-29 11:42:44 | N97: system | O97: 2026-05-15 11:58:32 | P97: 2026-05-15 11:58:32 | Y97: 27649870418
A98: 14363432 | B98: 6d88c10d-76dc-42d7-baf3-9ab030ba7e79 | D98: 30001082 | E98: ussd_funeral_leads_altitude_20260504 | J98: NA | K98: No Answer Autodial | L98: 31 | M98: 2026-05-29 11:42:43 | N98: system | O98: 2026-05-15 11:58:32 | P98: 2026-05-15 11:58:32 | Y98: 27715873418
A99: 14363435 | B99: 390b08cc-2bbe-4343-b646-3eb1f8805cb8 | D99: 30001082 | E99: ussd_funeral_leads_altitude_20260504 | J99: AA | K99: Answering Machine Autodial | L99: 31 | M99: 2026-05-29 11:42:43 | N99: system | O99: 2026-05-15 11:58:32 | P99: 2026-05-15 11:58:32 | Y99: 27828151787
A100: 14363439 | B100: 7166c4d9-eeb2-48f3-85e1-41b38a720857 | D100: 30001082 | E100: ussd_funeral_leads_altitude_20260504 | J100: AA | K100: Answering Machine Autodial | L100: 31 | M100: 2026-05-29 11:42:43 | N100: system | O100: 2026-05-15 11:58:32 | P100: 2026-05-15 11:58:32 | Y100: 27794171147
A101: 14363423 | B101: 0f88b395-57a1-4d6c-b698-6d1e62c8213c | D101: 30001082 | E101: ussd_funeral_leads_altitude_20260504 | J101: AA | K101: Answering Machine Autodial | L101: 31 | M101: 2026-05-29 11:42:42 | N101: system | O101: 2026-05-15 11:58:32 | P101: 2026-05-15 11:58:32 | Y101: 27795549599
A102: 14363412 | B102: 88cefad0-1f7a-417c-b7da-41f53be59d4a | D102: 30001082 | E102: ussd_funeral_leads_altitude_20260504 | J102: AA | K102: Answering Machine Autodial | L102: 31 | M102: 2026-05-29 11:42:39 | N102: system | O102: 2026-05-15 11:58:32 | P102: 2026-05-15 11:58:32 | Y102: 27760381881
A103: 14363378 | B103: f0af7d81-b781-4d78-919a-e653f7364d7b | D103: 30001082 | E103: ussd_funeral_leads_altitude_20260504 | J103: NA | K103: No Answer Autodial | L103: 31 | M103: 2026-05-29 11:42:38 | N103: system | O103: 2026-05-15 11:58:32 | P103: 2026-05-15 11:58:32 | Y103: 27714123120
A104: 14363397 | B104: 8bc1865c-f4f9-4fa1-8824-d774410b9fdd | D104: 30001082 | E104: ussd_funeral_leads_altitude_20260504 | J104: AA | K104: Answering Machine Autodial | L104: 31 | M104: 2026-05-29 11:42:38 | N104: system | O104: 2026-05-15 11:58:32 | P104: 2026-05-15 11:58:32 | Y104: 27723779029
A105: 14363342 | B105: 34868c94-d508-4692-8045-a67a81c1e3f6 | D105: 30001082 | E105: ussd_funeral_leads_altitude_20260504 | J105: AA | K105: Answering Machine Autodial | L105: 31 | M105: 2026-05-29 11:42:13 | N105: system | O105: 2026-05-15 11:58:32 | P105: 2026-05-15 11:58:32 | Y105: 27792604111
A106: 14363343 | B106: 5eeb15e9-33a8-4b62-b909-31dd22cd391c | D106: 30001082 | E106: ussd_funeral_leads_altitude_20260504 | J106: NA | K106: No Answer Autodial | L106: 31 | M106: 2026-05-29 11:42:13 | N106: system | O106: 2026-05-15 11:58:32 | P106: 2026-05-15 11:58:32 | Y106: 27713492799
A107: 14363346 | B107: 98a63f75-2d4d-434f-b7a2-6a3516a4844b | D107: 30001082 | E107: ussd_funeral_leads_altitude_20260504 | J107: AE | K107: Auto Engaged | L107: 31 | M107: 2026-05-29 11:42:13 | N107: system | O107: 2026-05-15 11:58:32 | P107: 2026-05-15 11:58:32 | Y107: 27724951053
A108: 14363330 | B108: 08a0a040-3d39-4803-aa14-d051535a3c2b | D108: 30001082 | E108: ussd_funeral_leads_altitude_20260504 | J108: NA | K108: No Answer Autodial | L108: 31 | M108: 2026-05-29 11:42:10 | N108: system | O108: 2026-05-15 11:58:32 | P108: 2026-05-15 11:58:32 | Y108: 27818674747
A109: 14363308 | B109: c30c6cb6-1d55-4676-bd84-a545a977ceac | D109: 30001082 | E109: ussd_funeral_leads_altitude_20260504 | J109: AA | K109: Answering Machine Autodial | L109: 31 | M109: 2026-05-29 11:42:09 | N109: system | O109: 2026-05-15 11:58:32 | P109: 2026-05-15 11:58:32 | Y109: 27637870796
... A120: 14363100 | B120: 1ad47df9-e0b0-4f9e-8342-7f6306ae93d5 | D120: 30001082 | E120: ussd_funeral_leads_altitude_20260504 | J120: ADC | K120: Auto Dial Disconnected | L120: 31 | M120: 2026-05-29 11:42:01 | N120: system | O120: 2026-05-15 11:58:32 | P120: 2026-05-15 11:58:32 | Y120: 27825372194
A121: 14363109 | B121: 2d728136-cfcc-47bb-b72a-9f77b37ae656 | D121: 30001082 | E121: ussd_funeral_leads_altitude_20260504 | H121: 27763059778 | J121: NA | K121: No Answer Autodial | L121: 31 | M121: 2026-05-29 11:42:01 | N121: system | O121: 2026-05-15 11:58:32 | P121: 2026-05-15 11:58:32 | Y121: 27763059778
A122: 14363023 | B122: b020ff68-c0db-4769-80cf-376a9869077f | D122: 30001082 | E122: ussd_funeral_leads_altitude_20260504 | J122: AA | K122: Answering Machine Autodial | L122: 31 | M122: 2026-05-29 11:42:00 | N122: system | O122: 2026-05-15 11:58:32 | P122: 2026-05-15 11:58:32 | Y122: 27722327440
A123: 14363070 | B123: ef80944c-13d0-4125-baf8-7212560e01f7 | D123: 30001082 | E123: ussd_funeral_leads_altitude_20260504 | J123: ADC | K123: Auto Dial Disconnected | L123: 31 | M123: 2026-05-29 11:42:00 | N123: system | O123: 2026-05-15 11:58:32 | P123: 2026-05-15 11:58:32 | Y123: 27675702617
A124: 14363071 | B124: c1209ded-fa9c-4a66-8f78-676e559fa090 | D124: 30001082 | E124: ussd_funeral_leads_altitude_20260504 | J124: AA | K124: Answering Machine Autodial | L124: 31 | M124: 2026-05-29 11:42:00 | N124: system | O124: 2026-05-15 11:58:32 | P124: 2026-05-15 11:58:32 | Y124: 27609846204
A125: 14363074 | B125: 46d293b5-186f-447c-b4b1-97867c839332 | D125: 30001082 | E125: ussd_funeral_leads_altitude_20260504 | J125: AA | K125: Answering Machine Autodial | L125: 31 | M125: 2026-05-29 11:42:00 | N125: system | O125: 2026-05-15 11:58:32 | P125: 2026-05-15 11:58:32 | Y125: 27713203818
A126: 14363079 | B126: a17f7336-0bed-4d21-80c1-62824e78bc43 | D126: 30001082 | E126: ussd_funeral_leads_altitude_20260504 | J126: AA | K126: Answering Machine Autodial | L126: 31 | M126: 2026-05-29 11:42:00 | N126: system | O126: 2026-05-15 11:58:32 | P126: 2026-05-15 11:58:32 | Y126: 27773763754
...

Sheet Campaign Analysis
A1: Campaign Analysis – USSD Funeral Leads
A4: Total Leads | B4: 566
A5: Unworked Leads (New Leads) | B5: 3
A6: Successful Contacts | B6: 123
A7: True Contacts | B7: 114
A8: Conversion | B8: 0.01590106
A9: True Sales (post QA) | B9: 9
A10: Collections
A11: Number of missed 1st Collections
A12: NTU
A13: Cancellations/Lapse
B16: Unsuccessful Contacts | C16: Lead Count | D16: Interested in Deal? | E16: Lead Count | F16: Successful Contacts | G16: Lead Count | H16: True Contacts | I16: Lead Count
B17: Answering Machine Autodial | C17: =IFERROR(VLOOKUP("Answering Machine Autodial",Pivot!$A$2:$B$29,2,FALSE),0) | D17: Sale Made - Completed Mandate | E17: =IFERROR(VLOOKUP("Sale Made - Completed Mandate",Pivot!$A$2:$B$29,2,FALSE),0) | F17: Already Contacted | G17: =IFERROR(VLOOKUP("Already Contacted",Pivot!$A$2:$B$29,2,FALSE),0) | H17: Client Hung Up | I17: =IFERROR(VLOOKUP("Client Hung Up",Pivot!$A$2:$B$29,2,FALSE),0)
B18: No Answer Autodial | C18: =IFERROR(VLOOKUP("No Answer Autodial",Pivot!$A$2:$B$29,2,FALSE),0) | D18: Sale Made - Pending Mandate | E18: =IFERROR(VLOOKUP("Sale Made - Pending Mandate",Pivot!$A$2:$B$29,2,FALSE),0) | F18: Existing Client | G18: =IFERROR(VLOOKUP("Existing Client",Pivot!$A$2:$B$29,2,FALSE),0) | H18: CallBack | I18: =IFERROR(VLOOKUP("CallBack",Pivot!$A$2:$B$29,2,FALSE),0)
B19: Auto Engaged | C19: =IFERROR(VLOOKUP("Auto Engaged",Pivot!$A$2:$B$29,2,FALSE),0) | D19: Sale Made | E19: =IFERROR(VLOOKUP("Sale Made",Pivot!$A$2:$B$29,2,FALSE),0) | F19: Unemployed | G19: =IFERROR(VLOOKUP("Unemployed",Pivot!$A$2:$B$29,2,FALSE),0) | H19: Not Interested | I19: =IFERROR(VLOOKUP("Not Interested",Pivot!$A$2:$B$29,2,FALSE),0)
B20: Disconnected Number Auto | C20: =IFERROR(VLOOKUP("Disconnected Number Auto",Pivot!$A$2:$B$29,2,FALSE),0) | D20: Tyme Bank Account Sale | E20: =IFERROR(VLOOKUP("Tyme Bank Account Sale",Pivot!$A$2:$B$29,2,FALSE),0) | F20: Wrong Number | G20: =IFERROR(VLOOKUP("Wrong Number",Pivot!$A$2:$B$29,2,FALSE),0) | H20: Not Interested Upfront | I20: =IFERROR(VLOOKUP("Not Interested Upfront",Pivot!$A$2:$B$29,2,FALSE),0)
B21: Answering Machine | C21: =IFERROR(VLOOKUP("Answering Machine",Pivot!$A$2:$B$29,2,FALSE),0) | D21: QA Rework | E21: =IFERROR(VLOOKUP("QA Rework",Pivot!$A$2:$B$29,2,FALSE),0) | F21: Do Not Call | G21: =IFERROR(VLOOKUP("Do Not Call",Pivot!$A$2:$B$29,2,FALSE),0) | H21: Cannot Afford Premium | I21: =IFERROR(VLOOKUP("Cannot Afford Premium",Pivot!$A$2:$B$29,2,FALSE),0)
B22: Selected | C22: =IFERROR(VLOOKUP("Selected",Pivot!$A$2:$B$29,2,FALSE),0) | F22: No Smartphones | G22: =IFERROR(VLOOKUP("No Smartphones",Pivot!$A$2:$B$29,2,FALSE),0) | H22: Not interested - Pitched | I22: =IFERROR(VLOOKUP("Not interested - Pitched",Pivot!$A$2:$B$29,2,FALSE),0)
B23: No Answer | C23: =IFERROR(VLOOKUP("No Answer",Pivot!$A$2:$B$29,2,FALSE),0) | F23: Client Deceased | G23: =IFERROR(VLOOKUP("Client Deceased",Pivot!$A$2:$B$29,2,FALSE),0) | H23: Affordability | I23: =IFERROR(VLOOKUP("Affordability",Pivot!$A$2:$B$29,2,FALSE),0)
B24: Busy Tone | C24: =IFERROR(VLOOKUP("Busy Tone",Pivot!$A$2:$B$29,2,FALSE),0) | F24: Right Party Not Available | G24: =IFERROR(VLOOKUP("Right Party Not Available",Pivot!$A$2:$B$29,2,FALSE),0) | H24: Quoted Client Not Interested | I24: =IFERROR(VLOOKUP("Quoted Client Not Interested",Pivot!$A$2:$B$29,2,FALSE),0)
B25: Dropped | C25: =IFERROR(VLOOKUP("Dropped",Pivot!$A$2:$B$29,2,FALSE),0) | F25: Client Overage Limit | G25: =IFERROR(VLOOKUP("Client Overage Limit",Pivot!$A$2:$B$29,2,FALSE),0) | H25: Not interested business does not use speed point mac | I25: =IFERROR(VLOOKUP("Not interested business does not use speed point mac",Pivot!$A$2:$B$29,2,FALSE),0)
B26: New | C26: =IFERROR(VLOOKUP("New",Pivot!$A$2:$B$29,2,FALSE),0) | F26: Language Barrier | G26: =IFERROR(VLOOKUP("Language Barrier",Pivot!$A$2:$B$29,2,FALSE),0) | H26: Call Back Technical Error | I26: =IFERROR(VLOOKUP("Call Back Technical Error",Pivot!$A$2:$B$29,2,FALSE),0)
B27: Call Dropped | C27: =IFERROR(VLOOKUP("Call Dropped",Pivot!$A$2:$B$29,2,FALSE),0) | F27: Non SA Citizen | G27: =IFERROR(VLOOKUP("Non SA Citizen",Pivot!$A$2:$B$29,2,FALSE),0) | H27: Not Interested Transaction Fees | I27: =IFERROR(VLOOKUP("Not Interested Transaction Fees",Pivot!$A$2:$B$29,2,FALSE),0)
B28: Inbound After Hours Drop | C28: =IFERROR(VLOOKUP("Inbound After Hours Drop",Pivot!$A$2:$B$29,2,FALSE),0) | F28: No Bank Account | G28: =IFERROR(VLOOKUP("No Bank Account",Pivot!$A$2:$B$29,2,FALSE),0) | H28: Cannot Afford | I28: =IFERROR(VLOOKUP("Cannot Afford",Pivot!$A$2:$B$29,2,FALSE),0)
B29: TPS Registered Number | C29: =IFERROR(VLOOKUP("TPS Registered Number",Pivot!$A$2:$B$29,2,FALSE),0) | F29: Client Underage | G29: =IFERROR(VLOOKUP("Client Underage",Pivot!$A$2:$B$29,2,FALSE),0) | H29: Not Interested Household Contents | I29: =IFERROR(VLOOKUP("Not Interested Household Contents",Pivot!$A$2:$B$29,2,FALSE),0)
B30: Temporary Disconnected Number | C30: =IFERROR(VLOOKUP("Temporary Disconnected Number",Pivot!$A$2:$B$29,2,FALSE),0) | F30: Go To The Branch | G30: =IFERROR(VLOOKUP("Go To The Branch",Pivot!$A$2:$B$29,2,FALSE),0) | H30: Call Back Hold | I30: =IFERROR(VLOOKUP("Call Back Hold",Pivot!$A$2:$B$29,2,FALSE),0)
B31: Bad Line Quality | C31: =IFERROR(VLOOKUP("Bad Line Quality",Pivot!$A$2:$B$29,2,FALSE),0) | F31: Completed | G31: =IFERROR(VLOOKUP("Completed",Pivot!$A$2:$B$29,2,FALSE),0) | H31: Declined Sale | I31: =IFERROR(VLOOKUP("Declined Sale",Pivot!$A$2:$B$29,2,FALSE),0)
B32: Inbound Abandon | C32: =IFERROR(VLOOKUP("Inbound Abandon",Pivot!$A$2:$B$29,2,FALSE),0) | F32: Cannot Afford Upfront Payment | G32: =IFERROR(VLOOKUP("Cannot Afford Upfront Payment",Pivot!$A$2:$B$29,2,FALSE),0)
B33: Outbound Pre-Routing Drop | C33: =IFERROR(VLOOKUP("Outbound Pre-Routing Drop",Pivot!$A$2:$B$29,2,FALSE),0) | F33: Account Suspended | G33: =IFERROR(VLOOKUP("Account Suspended",Pivot!$A$2:$B$29,2,FALSE),0)
B34: Engaged | C34: =IFERROR(VLOOKUP("Engaged",Pivot!$A$2:$B$29,2,FALSE),0) | F34: Insured at another company | G34: =IFERROR(VLOOKUP("Insured at another company",Pivot!$A$2:$B$29,2,FALSE),0)
B35: Disconnected | C35: =IFERROR(VLOOKUP("Disconnected",Pivot!$A$2:$B$29,2,FALSE),0) | F35: Scheduled Appointment | G35: =IFERROR(VLOOKUP("Scheduled Appointment",Pivot!$A$2:$B$29,2,FALSE),0)
B36: CONGESTED | C36: =IFERROR(VLOOKUP("CONGESTED",Pivot!$A$2:$B$29,2,FALSE),0) | F36: Refund Request | G36: =IFERROR(VLOOKUP("Refund Request",Pivot!$A$2:$B$29,2,FALSE),0)
B37: Flow Inbound Abandon | C37: =IFERROR(VLOOKUP("Flow Inbound Abandon",Pivot!$A$2:$B$29,2,FALSE),0) | F37: Does Not Qualify | G37: =IFERROR(VLOOKUP("Does Not Qualify",Pivot!$A$2:$B$29,2,FALSE),0)
B38: Multiple Calls | C38: =IFERROR(VLOOKUP("Multiple Calls",Pivot!$A$2:$B$29,2,FALSE),0) | F38: Does Not Have a Business | G38: =IFERROR(VLOOKUP("Does Not Have a Business",Pivot!$A$2:$B$29,2,FALSE),0)
B39: Missed | C39: =IFERROR(VLOOKUP("Missed",Pivot!$A$2:$B$29,2,FALSE),0) | F39: Refer To Store - Doesn't want to complete online | G39: =IFERROR(VLOOKUP("Refer To Store - Doesn't want to complete online",Pivot!$A$2:$B$29,2,FALSE),0)
B40: Answered | C40: =IFERROR(VLOOKUP("Answered",Pivot!$A$2:$B$29,2,FALSE),0) | F40: Does Not Need It Now | G40: =IFERROR(VLOOKUP("Does Not Need It Now",Pivot!$A$2:$B$29,2,FALSE),0)
B41: Customer drop | C41: =IFERROR(VLOOKUP("Customer drop",Pivot!$A$2:$B$29,2,FALSE),0) | F41: Technical Issue | G41: =IFERROR(VLOOKUP("Technical Issue",Pivot!$A$2:$B$29,2,FALSE),0)
B42: Auto Dial Disconnected | C42: =IFERROR(VLOOKUP("Auto Dial Disconnected",Pivot!$A$2:$B$29,2,FALSE),0) | F42: Unsuccessful Application | G42: =IFERROR(VLOOKUP("Unsuccessful Application",Pivot!$A$2:$B$29,2,FALSE),0)
B43: Disconnected Number Temporary | C43: =IFERROR(VLOOKUP("Disconnected Number Temporary",Pivot!$A$2:$B$29,2,FALSE),0)
A46: TOTAL LEADS DIALLED | B46: =SUM(C17:C43)+SUM(E17:E21)
A48: CAMPAIGN STATISTICS
A49: Successful Contacts | B49: =SUM(F17:F21)
A50: True Contacts (TC) | B50: =SUM(I17:I31)
A51: Unworkable Leads | B51: =SUM(G17:G42)
A52: Conversions | B52: =F17
A53: Conversion Ratio (vs TC) | B53: =B51/B49
A54: Contact Ratio | B54: =(B48+B49)/B46
A58: Top 5 Statuses | B58: Count | C58: % Contribution
A59: Answering Machine Autodial | B59: 116 | C59: =B59/B46
A60: Auto Dial Disconnected | B60: 101 | C60: =B60/B46
A61: No Answer Autodial | B61: 64 | C61: =B61/B46
A62: Auto Engaged | B62: 41 | C62: =B62/B46
A63: Callback | B63: 39 | C63: =B63/B46
